Workbook

Sheet gesprekken per thema
A1: Onderwerp | B1: nummer | C1: Chauffeurnaam | D1: Datum | E1: Info | F1: Maand | G1: Jaar | H1: Aantal | I1: in dienst
A2: Ziekteverzuim: vergadering | B2: 3793 | C2: =VLOOKUP(B2,chauffeurslijst!A:B,2,0) -> Makelberge Michel | D2: 42395 | E2: verg: soc dienst neemt contact op | F2: =MONTH(D2) -> 1 | G2: =YEAR(D2) -> 2016 | H2: =COUNTIF(B:B,B2) -> 2 | I2: =VLOOKUP(B2,'controle 2022'!A:D,4,0) -> In dienst
A3: vroegrijden | B3: 3793 | C3: Makelberge Michel | D3: 43979 | E3: ED mail 12% extreem te vroeg en 32% te vroeg Totaal 44% te vroeg Covid 19? | F3: =MONTH(D3) -> 5 | G3: =YEAR(D3) -> 2020 | H3: =COUNTIF(B:B,B3) -> 2 | I3: =VLOOKUP(B3,'controle 2022'!A:D,4,0) -> In dienst
A4: Ongevallen/rijstijl | B4: 3926 | C4: De Clercq Marc | D4: 43580 | E4: Gesprek nav. ongeval eigen schade: bij binnenrijden sp 16 hermelijn2werkplaats steunbalk passerelle geraakt en geen melding van gemaakt. Besef van fout. In samenspraak met SH gn VVF maar bevestigingsbrief. | F4: =MONTH(D4) -> 4 | G4: =YEAR(D4) -> 2019 | H4: =COUNTIF(B:B,B4) -> 4 | I4: =VLOOKUP(B4,'controle 2022'!A:D,4,0) -> In dienst
A5: Vroegrijden: informeel | B5: 3926 | C5: De Clercq Marc | D5: 43812 | E5: Bart VDB: in de wandelgangen aangesproken mbt. slechte resultaten maand sept. tem. nov (steeds >30%), Hij weet dat hij er op moet letten en dat er werk aan de winkel is. Is een habitué in het te vroeg rijden. Bij een volgende vaststelling melding in chauffeurbeheer.... | F5: =MONTH(D5) -> 12 | G5: =YEAR(D5) -> 2019 | H5: =COUNTIF(B:B,B5) -> 4 | I5: =VLOOKUP(B5,'controle 2022'!A:D,4,0) -> In dienst
A6: Vroegrijden: informeel | B6: 3926 | C6: De Clercq Marc | D6: 43866 | E6: Bart VDB: maand dec. 2019 was beter 17,65% te vroege ritten waarvan 4,14% extremen.Echter jan. 2020 terug herval…35,71% te vroeg waarvan 1,79% extremen. Hem aangemoedigd dat hij het wel kan (zie dec.) en zijn uiterste best moet doen om zijn slechte gewoonte af te leren. In chauffeurbeheer gestoken onder coachinggesprekken. | F6: =MONTH(D6) -> 2 | G6: =YEAR(D6) -> 2020 | H6: =COUNTIF(B:B,B6) -> 4 | I6: =VLOOKUP(B6,'controle 2022'!A:D,4,0) -> In dienst
A7: Monitoring: te vroeg rijden | B7: 3926 | C7: De Clercq Marc | D7: 44384 | E7: Bart VDB Marc persoonlijk aangesproken: Wegens nieuwe aanspreekgrens >20% vanaf juni , nav. 22,75% totaal te vroeg (geen extremen). Marc heeft op vlak van te vroeg rijden wel een verleden maar geleden van jan. 2021 dat hij nog eens boven de 30% zat. Febr. tem. mei tss 10 & 20% steeds. Gevraagd nog een kleine inspanning te doen, immers hij heeft het afgelopen half jaar bewezen dat hij het wel kan. | F7: =MONTH(D7) -> 7 | G7: =YEAR(D7) -> 2021 | H7: =COUNTIF(B:B,B7) -> 4 | I7: =VLOOKUP(B7,'controle 2022'!A:D,4,0) -> In dienst
A8: Ziekteverzuim: vergadering | B8: 4193 | C8: =VLOOKUP(B8,chauffeurslijst!A:B,2,0) -> De Schepper Geert | D8: 42571 | E8: verg: opvolgen | F8: =MONTH(D8) -> 7 | G8: =YEAR(D8) -> 2016 | H8: =COUNTIF(B:B,B8) -> 6 | I8: =VLOOKUP(B8,'controle 2022'!A:D,4,0) -> In dienst
A9: Ziekteverzuim: vergadering | B9: 4193 | C9: =VLOOKUP(B9,chauffeurslijst!A:B,2,0) -> De Schepper Geert | D9: 42982 | E9: verg: opvolgen | F9: =MONTH(D9) -> 9 | G9: =YEAR(D9) -> 2017 | H9: =COUNTIF(B:B,B9) -> 6 | I9: =VLOOKUP(B9,'controle 2022'!A:D,4,0) -> In dienst
A10: Ziekteverzuim: informeel | B10: 4193 | C10: =VLOOKUP(B10,chauffeurslijst!A:B,2,0) -> De Schepper Geert | D10: 43038 | E10: Geert vroeg vroege diensten op 24, 25 en 26/10, daar is niet op ingegaan wegens maximaal aantal AD/maand bereikt; heeft zich ziek gezet op 24/10, herneemt vanaf 28/10 (maar had niet verwittigt dat hij herneemt) | F10: =MONTH(D10) -> 10 | G10: =YEAR(D10) -> 2017 | H10: =COUNTIF(B:B,B10) -> 6 | I10: =VLOOKUP(B10,'controle 2022'!A:D,4,0) -> In dienst
A11: Informeel | B11: 4193 | C11: =VLOOKUP(B11,chauffeurslijst!A:B,2,0) -> De Schepper Geert | D11: 43070 | E11: nav agressiegeval vorige week 2 weken tramdiensten | F11: =MONTH(D11) -> 12 | G11: =YEAR(D11) -> 2017 | H11: =COUNTIF(B:B,B11) -> 6 | I11: =VLOOKUP(B11,'controle 2022'!A:D,4,0) -> In dienst
A12: Ziekteverzuim | B12: 4193 | C12: =VLOOKUP(B12,chauffeurslijst!A:B,2,0) -> De Schepper Geert | D12: 43118 | E12: cr: standaardgesprek verzuim, voor RC al stappen ondernomen voor gesprek | F12: =MONTH(D12) -> 1 | G12: =YEAR(D12) -> 2018 | H12: =COUNTIF(B:B,B12) -> 6 | I12: =VLOOKUP(B12,'controle 2022'!A:D,4,0) -> In dienst
A13: informeel | B13: 4193 | C13: De Schepper Geert | D13: 44777 | E13: info YDC: gaat okt 2022 met pensioen | F13: =MONTH(D13) -> 8 | G13: =YEAR(D13) -> 2022 | H13: =COUNTIF(B:B,B13) -> 6 | I13: =VLOOKUP(B13,'controle 2022'!A:D,4,0) -> In dienst
A14: informeel | B14: 4276 | C14: Mostaert R | D14: 43726 | E14: LVV : aan zuid aangesproken door rudy omdat oude vrouw gevallen was bij het afstappen van de bus. Hij was er niet gerust in. Reiziger zei dat ze juist naar de dokter ging om de hoek. Ik heb die dokter gebeld en zei dat alles onder controle was. Rudy hiervan ingelicht. | F14: =MONTH(D14) -> 9 | G14: =YEAR(D14) -> 2019 | H14: =COUNTIF(B:B,B14) -> 1 | I14: =VLOOKUP(B14,'controle 2022'!A:D,4,0) -> In dienst
A15: Ziekteverzuim: vergadering | B15: 4440 | C15: =VLOOKUP(B15,chauffeurslijst!A:B,2,0) -> De Roo Jan | D15: 41582 | E15: verg 04/11/13: gesprek CR na volgende ZI | F15: =MONTH(D15) -> 11 | G15: =YEAR(D15) -> 2013 | H15: =COUNTIF(B:B,B15) -> 4 | I15: =VLOOKUP(B15,'controle 2022'!A:D,4,0) -> In dienst
A16: Ziekteverzuim: vergadering | B16: 4440 | C16: =VLOOKUP(B16,chauffeurslijst!A:B,2,0) -> De Roo Jan | D16: 42010 | E16: verg 06/01/15: zal nog tijdje tuis zijn, gaat niet goed met hem, soc dienst volgt op | F16: =MONTH(D16) -> 1 | G16: =YEAR(D16) -> 2015 | H16: =COUNTIF(B:B,B16) -> 4 | I16: =VLOOKUP(B16,'controle 2022'!A:D,4,0) -> In dienst
A17: Ziekteverzuim: informeel | B17: 4440 | C17: =VLOOKUP(B17,chauffeurslijst!A:B,2,0) -> De Roo Jan | D17: 42905 | E17: melding van soc dienst dat het niet goed gaat met Jan | F17: =MONTH(D17) -> 6 | G17: =YEAR(D17) -> 2017 | H17: =COUNTIF(B:B,B17) -> 4 | I17: =VLOOKUP(B17,'controle 2022'!A:D,4,0) -> In dienst
A18: Ziekteverzuim: informeel | B18: 4440 | C18: =VLOOKUP(B18,chauffeurslijst!A:B,2,0) -> De Roo Jan | D18: 42906 | E18: soc dienst: Ik ben bij Jan geweest gisteren. Zijn ziekte-attest is binnen. Volgens mij zal de afwezigheid niet zo lang duren als de vorige keer. Er werden nu al stappen gezet om de situatie aan te pakken. | F18: =MONTH(D18) -> 6 | G18: =YEAR(D18) -> 2017 | H18: =COUNTIF(B:B,B18) -> 4 | I18: =VLOOKUP(B18,'controle 2022'!A:D,4,0) -> In dienst
A19: Geldafgifte | B19: 4522 | C19: =VLOOKUP(B19,chauffeurslijst!A:B,2,0) -> Dierinck Charles | D19: 42017 | E19: 13/01/15: (tel.) zal vanaf nu de laatste werkdag storten ipv de eerste | F19: =MONTH(D19) -> 1 | G19: =YEAR(D19) -> 2015 | H19: =COUNTIF(B:B,B19) -> 2 | I19: =VLOOKUP(B19,'controle 2022'!A:D,4,0) -> In dienst
A20: Ziekteverzuim: vergadering | B20: 4522 | C20: =VLOOKUP(B20,chauffeurslijst!A:B,2,0) -> Dierinck Charles | D20: 42571 | E20: verg: soc dienst heeft contact gehad, operatie | F20: =MONTH(D20) -> 7 | G20: =YEAR(D20) -> 2016 | H20: =COUNTIF(B:B,B20) -> 2 | I20: =VLOOKUP(B20,'controle 2022'!A:D,4,0) -> In dienst
A21: Ziekteverzuim: vergadering | B21: 4523 | C21: =VLOOKUP(B21,chauffeurslijst!A:B,2,0) -> Lammens Eric | D21: 42571 | E21: verg: opvolgen | F21: =MONTH(D21) -> 7 | G21: =YEAR(D21) -> 2016 | H21: =COUNTIF(B:B,B21) -> 1 | I21: =VLOOKUP(B21,'controle 2022'!A:D,4,0) -> In dienst
A22: Evaluatie lijnverantw. | B22: 4525 | C22: Geert Vanthomme | D22: 44705 | E22: Bakken ervaring en kennis , die hij nog steeds met een bepaald enthousiasme overbrengt, Brengt heel veel verbetervoorstellen en gaat vlot in dialoog . Durft nogal licht ontvlambaar te zijn als er iets misloopt , maar weet dit even snel een plaats te geven. | F22: =MONTH(D22) -> 5 | G22: =YEAR(D22) -> 2022 | H22: =COUNTIF(B:B,B22) -> 1 | I22: =VLOOKUP(B22,'controle 2022'!A:D,4,0) -> In dienst
A23: Ziekteverzuim: vergadering | B23: 4608 | C23: =VLOOKUP(B23,chauffeurslijst!A:B,2,0) -> Steenbrugge Johan | D23: 41703 | E23: verg 05/03/14: geen actie | F23: =MONTH(D23) -> 3 | G23: =YEAR(D23) -> 2014 | H23: =COUNTIF(B:B,B23) -> 15 | I23: =VLOOKUP(B23,'controle 2022'!A:D,4,0) -> In dienst
A24: Ziekteverzuim: vergadering | B24: 4608 | C24: =VLOOKUP(B24,chauffeurslijst!A:B,2,0) -> Steenbrugge Johan | D24: 42109 | E24: verg 15/04/15: soc dienst kent het dossier en volgt op, is in behandeling | F24: =MONTH(D24) -> 4 | G24: =YEAR(D24) -> 2015 | H24: =COUNTIF(B:B,B24) -> 15 | I24: =VLOOKUP(B24,'controle 2022'!A:D,4,0) -> In dienst
A25: Ziekteverzuim: vergadering | B25: 4608 | C25: =VLOOKUP(B25,chauffeurslijst!A:B,2,0) -> Steenbrugge Johan | D25: 42571 | E25: verg: soc dienst volgt op | F25: =MONTH(D25) -> 7 | G25: =YEAR(D25) -> 2016 | H25: =COUNTIF(B:B,B25) -> 15 | I25: =VLOOKUP(B25,'controle 2022'!A:D,4,0) -> In dienst
A26: Ziekteverzuim | B26: 4608 | C26: =VLOOKUP(B26,chauffeurslijst!A:B,2,0) -> Steenbrugge Johan | D26: 42747 | E26: sw : samenloop van omstandigheden, geen reden tot verder verzuim, goed dossier | F26: =MONTH(D26) -> 1 | G26: =YEAR(D26) -> 2017 | H26: =COUNTIF(B:B,B26) -> 15 | I26: =VLOOKUP(B26,'controle 2022'!A:D,4,0) -> In dienst
A27: Ziekteverzuim: vergadering | B27: 4608 | C27: =VLOOKUP(B27,chauffeurslijst!A:B,2,0) -> Steenbrugge Johan | D27: 42754 | E27: verg: gesprek plaatsgevonden | F27: =MONTH(D27) -> 1 | G27: =YEAR(D27) -> 2017 | H27: =COUNTIF(B:B,B27) -> 15 | I27: =VLOOKUP(B27,'controle 2022'!A:D,4,0) -> In dienst
A28: Ziekteverzuim: vergadering | B28: 4608 | C28: =VLOOKUP(B28,chauffeurslijst!A:B,2,0) -> Steenbrugge Johan | D28: 43278 | E28: verg: gesprek inplannen - start traject | F28: =MONTH(D28) -> 6 | G28: =YEAR(D28) -> 2018 | H28: =COUNTIF(B:B,B28) -> 15 | I28: =VLOOKUP(B28,'controle 2022'!A:D,4,0) -> In dienst
A29: Ziekteverzuim | B29: 4608 | C29: =VLOOKUP(B29,chauffeurslijst!A:B,2,0) -> Steenbrugge Johan | D29: 43286 | E29: cr: start traject (rugklachten + thuis geweest met tennis- en golfelleboog) - verder blanco dossier | F29: =MONTH(D29) -> 7 | G29: =YEAR(D29) -> 2018 | H29: =COUNTIF(B:B,B29) -> 15 | I29: =VLOOKUP(B29,'controle 2022'!A:D,4,0) -> In dienst
A30: voorval met collega | B30: 4608 | C30: Steenbrugge Johan | D30: 43640 | E30: LVV : gesprek ivm voorval met collega (Idris Ozdemir) | F30: =MONTH(D30) -> 6 | G30: =YEAR(D30) -> 2019 | H30: =COUNTIF(B:B,B30) -> 15 | I30: =VLOOKUP(B30,'controle 2022'!A:D,4,0) -> In dienst
A31: Ziekteverzuim | B31: 4608 | C31: =VLOOKUP(B31,[1]chauffeurslijst!A:B,2,0) -> Steenbrugge Johan | D31: 44091 | E31: lvdv : telefonisch gesprek met Johan. Is reeds 1 maand thuis met rugklachten, kan pas op 21/09/20 terug naar zijn arts. Er zal waarschijnlijk een verlenging volgen. Hij heeft ook opnieuw last van zijn luchtwegen. | F31: =MONTH(D31) -> 9 | G31: =YEAR(D31) -> 2020 | H31: =COUNTIF(B:B,B31) -> 15 | I31: =VLOOKUP(B31,'controle 2022'!A:D,4,0) -> In dienst
A32: Ziekteverzuim | B32: 4608 | C32: =VLOOKUP(B32,[1]chauffeurslijst!A:B,2,0) -> Steenbrugge Johan | D32: 44147 | E32: LVV : telefonisch gesprek met Johan. Heeft terug verlenging gehad. Hij heeft last van jicht. | F32: =MONTH(D32) -> 11 | G32: =YEAR(D32) -> 2020 | H32: =COUNTIF(B:B,B32) -> 15 | I32: =VLOOKUP(B32,'controle 2022'!A:D,4,0) -> In dienst
A33: Ziekteverzuim | B33: 4608 | C33: =VLOOKUP(B33,[1]chauffeurslijst!A:B,2,0) -> Steenbrugge Johan | D33: 44159 | E33: LVV : gesprek ivm 4 keer ziek in 1 jaar, samen 153 dagen, bevestigd met brief | F33: =MONTH(D33) -> 11 | G33: =YEAR(D33) -> 2020 | H33: =COUNTIF(B:B,B33) -> 15 | I33: =VLOOKUP(B33,'controle 2022'!A:D,4,0) -> In dienst
A34: Ziekteverzuim | B34: 4608 | C34: =VLOOKUP(B34,[1]chauffeurslijst!A:B,2,0) -> Steenbrugge Johan | D34: 44741 | E34: gesprek SH + LVV : luisteren naar perspectieven naar herneming toe - langdurig ziek | F34: =MONTH(D34) -> 6 | G34: =YEAR(D34) -> 2022 | H34: =COUNTIF(B:B,B34) -> 15 | I34: =VLOOKUP(B34,'controle 2022'!A:D,4,0) -> In dienst
A35: Ziekteverzuim | B35: 4608 | C35: =VLOOKUP(B35,[1]chauffeurslijst!A:B,2,0) -> Steenbrugge Johan | D35: 45398 | E35: gesprek LVV : 4 x ziek/jaar, verder goed dossier | F35: =MONTH(D35) -> 4 | G35: =YEAR(D35) -> 2024 | H35: =COUNTIF(B:B,B35) -> 15 | I35: =VLOOKUP(B35,'controle 2022'!A:D,4,0) -> In dienst
A36: verzuim : informeel | B36: 4608 | C36: =VLOOKUP(B36,[1]chauffeurslijst!A:B,2,0) -> Steenbrugge Johan | D36: 45593 | E36: tel LVV: Johan had eerst een attest tem 26/10/2024 en had al verwittigd dat hij het werk zou hervatten. Zijn rug is opnieuw geblokeerd en hij krijgt zware medicatie en moet veel rusten | F36: =MONTH(D36) -> 10 | G36: =YEAR(D36) -> 2024 | H36: =COUNTIF(B:B,B36) -> 15 | I36: =VLOOKUP(B36,'controle 2022'!A:D,4,0) -> In dienst
A37: verzuim : informeel | B37: 4608 | C37: =VLOOKUP(B37,[1]chauffeurslijst!A:B,2,0) -> Steenbrugge Johan | D37: 45999 | E37: tel. LVV: Johan is ziek van 10/11 tem 03/12/2025 met rugpijn. Hij heeft het werk hervat maar na 3 dagen opnieuw onhoudbare pijn in rug. Ondertussen attest tem 19/12/2025. Hij moet hiervoor onder de MRI gaan. Dit kan pas op 28/02/2026 | F37: =MONTH(D37) -> 12 | G37: =YEAR(D37) -> 2025
A38: Geldafgifte | B38: 4624 | C38: =VLOOKUP(B38,chauffeurslijst!A:B,2,0) -> Declercq Erik | D38: 40471 | E38: elke barema storten | F38: =MONTH(D38) -> 10 | G38: =YEAR(D38) -> 2010 | H38: =COUNTIF(B:B,B38) -> 12 | I38: =VLOOKUP(B38,'controle 2022'!A:D,4,0) -> In dienst
A39: Geldafgifte | B39: 4624 | C39: =VLOOKUP(B39,chauffeurslijst!A:B,2,0) -> Declercq Erik | D39: 41232 | E39: (CR + IVC): laatste kans (ziekte, TL en geldafgifte), dagelijks storten | F39: =MONTH(D39) -> 11 | G39: =YEAR(D39) -> 2012 | H39: =COUNTIF(B:B,B39) -> 12 | I39: =VLOOKUP(B39,'controle 2022'!A:D,4,0) -> In dienst
A40: Ziekteverzuim | B40: 4624 | C40: =VLOOKUP(B40,chauffeurslijst!A:B,2,0) -> Declercq Erik | D40: 41232 | E40: 19/11/12 (CR + IVC): laatste kans (ziekte, TL en geldafgifte) | F40: =MONTH(D40) -> 11 | G40: =YEAR(D40) -> 2012 | H40: =COUNTIF(B:B,B40) -> 12 | I40: =VLOOKUP(B40,'controle 2022'!A:D,4,0) -> In dienst
A41: Te laat komen | B41: 4624 | C41: =VLOOKUP(B41,chauffeurslijst!A:B,2,0) -> Declercq Erik | D41: 41232 | E41: 19/11/12 (CR + IVC): laatste kans (ziekte, TL en geldafgifte) | F41: =MONTH(D41) -> 11 | G41: =YEAR(D41) -> 2012 | H41: =COUNTIF(B:B,B41) -> 12 | I41: =VLOOKUP(B41,'controle 2022'!A:D,4,0) -> In dienst
A42: Geldafgifte | B42: 4624 | C42: =VLOOKUP(B42,chauffeurslijst!A:B,2,0) -> Declercq Erik | D42: 41352 | E42: brief: geldafgifte blijft aandachtspunt | F42: =MONTH(D42) -> 3 | G42: =YEAR(D42) -> 2013 | H42: =COUNTIF(B:B,B42) -> 12 | I42: =VLOOKUP(B42,'controle 2022'!A:D,4,0) -> In dienst
A43: Melding controle | B43: 4624 | C43: =VLOOKUP(B43,chauffeurslijst!A:B,2,0) -> Declercq Erik | D43: 41366 | E43: 02/04/13: melding van Pascal Verlinden over gebrekkige hygiëne en vuile kledij van chauffeur => doorgegeven aan sociale dienst | F43: =MONTH(D43) -> 4 | G43: =YEAR(D43) -> 2013 | H43: =COUNTIF(B:B,B43) -> 12 | I43: =VLOOKUP(B43,'controle 2022'!A:D,4,0) -> In dienst
A44: Geldafgifte | B44: 4624 | C44: =VLOOKUP(B44,chauffeurslijst!A:B,2,0) -> Declercq Erik | D44: 41488 | E44: nazicht kas 02/08/13: NOK, op te nemen met P | F44: =MONTH(D44) -> 8 | G44: =YEAR(D44) -> 2013 | H44: =COUNTIF(B:B,B44) -> 12 | I44: =VLOOKUP(B44,'controle 2022'!A:D,4,0) -> In dienst
A45: Geldafgifte | B45: 4624 | C45: =VLOOKUP(B45,chauffeurslijst!A:B,2,0) -> Declercq Erik | D45: 41570 | E45: 3 d eff schorsing + bevestiging laatste verwittiging | F45: =MONTH(D45) -> 10 | G45: =YEAR(D45) -> 2013 | H45: =COUNTIF(B:B,B45) -> 12 | I45: =VLOOKUP(B45,'controle 2022'!A:D,4,0) -> In dienst
A46: Te laat komen | B46: 4624 | C46: =VLOOKUP(B46,chauffeurslijst!A:B,2,0) -> Declercq Erik | D46: 41570 | E46: 23/10/13: 3 d eff schorsing + bevestiging laatste kans | F46: =MONTH(D46) -> 10 | G46: =YEAR(D46) -> 2013 | H46: =COUNTIF(B:B,B46) -> 12 | I46: =VLOOKUP(B46,'controle 2022'!A:D,4,0) -> In dienst
A47: Te laat komen | B47: 4624 | C47: =VLOOKUP(B47,chauffeurslijst!A:B,2,0) -> Declercq Erik | D47: 41660 | E47: nazicht 21/01/14: geen nieuwe vvf | F47: =MONTH(D47) -> 1 | G47: =YEAR(D47) -> 2014 | H47: =COUNTIF(B:B,B47) -> 12 | I47: =VLOOKUP(B47,'controle 2022'!A:D,4,0) -> In dienst
A48: Geldafgifte | B48: 4624 | C48: =VLOOKUP(B48,chauffeurslijst!A:B,2,0) -> Declercq Erik | D48: 42118 | E48: 24/04/15: gebeld, gewezen op feit dat hij niet mag vervallen in oude gewoontes. | F48: =MONTH(D48) -> 4 | G48: =YEAR(D48) -> 2015 | H48: =COUNTIF(B:B,B48) -> 12 | I48: =VLOOKUP(B48,'controle 2022'!A:D,4,0) -> In dienst
A49: Ziekteverzuim: informeel | B49: 4624 | C49: =VLOOKUP(B49,chauffeurslijst!A:B,2,0) -> Declercq Erik | D49: 43425 | E49: opvolging LZ: suiker te hoog, moet medicatie nemen, deze week en volgende week bloedanalyse, indien suiker voldoende laag, kan hij hernemen in dec; opgemerkt door arbeidsgeneesheer | F49: =MONTH(D49) -> 11 | G49: =YEAR(D49) -> 2018 | H49: =COUNTIF(B:B,B49) -> 12 | I49: =VLOOKUP(B49,'controle 2022'!A:D,4,0) -> In dienst
A50: Ziekteverzuim | B50: 4764 | C50: =VLOOKUP(B50,chauffeurslijst!A:B,2,0) -> Beke Erik | D50: 40967 | E50: 40967 | F50: =MONTH(D50) -> 2 | G50: =YEAR(D50) -> 2012 | H50: =COUNTIF(B:B,B50) -> 24 | I50: =VLOOKUP(B50,'controle 2022'!A:D,4,0) -> In dienst
A51: Ziekteverzuim: vergadering | B51: 4764 | C51: =VLOOKUP(B51,chauffeurslijst!A:B,2,0) -> Beke Erik | D51: 41703 | E51: verg 05/03/14: dossier in detail te bekijken | F51: =MONTH(D51) -> 3 | G51: =YEAR(D51) -> 2014 | H51: =COUNTIF(B:B,B51) -> 24 | I51: =VLOOKUP(B51,'controle 2022'!A:D,4,0) -> In dienst
A52: Ziekteverzuim: vergadering | B52: 4764 | C52: =VLOOKUP(B52,chauffeurslijst!A:B,2,0) -> Beke Erik | D52: 41765 | E52: verg 06/05/14: gesprek CR na ziekte | F52: =MONTH(D52) -> 5 | G52: =YEAR(D52) -> 2014 | H52: =COUNTIF(B:B,B52) -> 24 | I52: =VLOOKUP(B52,'controle 2022'!A:D,4,0) -> In dienst
A53: Ziekteverzuim | B53: 4764 | C53: =VLOOKUP(B53,chauffeurslijst!A:B,2,0) -> Beke Erik | D53: 41824 | E53: 41824 | F53: =MONTH(D53) -> 7 | G53: =YEAR(D53) -> 2014 | H53: =COUNTIF(B:B,B53) -> 24 | I53: =VLOOKUP(B53,'controle 2022'!A:D,4,0) -> In dienst
A54: Onregelmatigheden | B54: 4764 | C54: =VLOOKUP(B54,chauffeurslijst!A:B,2,0) -> Beke Erik | D54: 42005 | E54: 01/01/2015 : brief ivm "niet aansluiten perslucht in 2014" | F54: =MONTH(D54) -> 1 | G54: =YEAR(D54) -> 2015 | H54: =COUNTIF(B:B,B54) -> 24 | I54: =VLOOKUP(B54,'controle 2022'!A:D,4,0) -> In dienst
A55: Algemeen functioneren | B55: 4764 | C55: =VLOOKUP(B55,chauffeurslijst!A:B,2,0) -> Beke Erik | D55: 42286 | E55: 09/10/2015(sw) : rijdt laatste rit rechstreeks binnen (melding door collega's) | F55: =MONTH(D55) -> 10 | G55: =YEAR(D55) -> 2015 | H55: =COUNTIF(B:B,B55) -> 24 | I55: =VLOOKUP(B55,'controle 2022'!A:D,4,0) -> In dienst
A56: Ziekteverzuim: vergadering | B56: 4764 | C56: =VLOOKUP(B56,chauffeurslijst!A:B,2,0) -> Beke Erik | D56: 42626 | E56: verg: gesprek regio na volgende ZI | F56: =MONTH(D56) -> 9 | G56: =YEAR(D56) -> 2016 | H56: =COUNTIF(B:B,B56) -> 24 | I56: =VLOOKUP(B56,'controle 2022'!A:D,4,0) -> In dienst
A57: Ziekteverzuim | B57: 4764 | C57: =VLOOKUP(B57,chauffeurslijst!A:B,2,0) -> Beke Erik | D57: 42692 | E57: sw : standaard verzuimgesprek | F57: =MONTH(D57) -> 11 | G57: =YEAR(D57) -> 2016 | H57: =COUNTIF(B:B,B57) -> 24 | I57: =VLOOKUP(B57,'controle 2022'!A:D,4,0) -> In dienst
A58: Ziekteverzuim: informeel | B58: 4764 | C58: =VLOOKUP(B58,chauffeurslijst!A:B,2,0) -> Beke Erik | D58: 42769 | E58: mail soc dienst: terug naar huis gestuurd door arbeidsgeneesheer | F58: =MONTH(D58) -> 2 | G58: =YEAR(D58) -> 2017 | H58: =COUNTIF(B:B,B58) -> 24 | I58: =VLOOKUP(B58,'controle 2022'!A:D,4,0) -> In dienst
A59: Ziekteverzuim: vergadering | B59: 4764 | C59: =VLOOKUP(B59,chauffeurslijst!A:B,2,0) -> Beke Erik | D59: 42982 | E59: verg: zag het even niet zitten, rust ingelast, lijkt nu over, eens luisteren hoe het verloopt (telefonisch) | F59: =MONTH(D59) -> 9 | G59: =YEAR(D59) -> 2017 | H59: =COUNTIF(B:B,B59) -> 24 | I59: =VLOOKUP(B59,'controle 2022'!A:D,4,0) -> In dienst
A60: Ziekteverzuim: informeel | B60: 4764 | C60: =VLOOKUP(B60,chauffeurslijst!A:B,2,0) -> Beke Erik | D60: 42983 | E60: tel. CR: gaat beter, zeker met het deeltijds werken | F60: =MONTH(D60) -> 9 | G60: =YEAR(D60) -> 2017 | H60: =COUNTIF(B:B,B60) -> 24 | I60: =VLOOKUP(B60,'controle 2022'!A:D,4,0) -> In dienst
A61: Onregelmatigheden | B61: 4764 | C61: =VLOOKUP(B61,chauffeurslijst!A:B,2,0) -> Beke Erik | D61: 43060 | E61: pv roken achter stuur | F61: =MONTH(D61) -> 11 | G61: =YEAR(D61) -> 2017 | H61: =COUNTIF(B:B,B61) -> 24 | I61: =VLOOKUP(B61,'controle 2022'!A:D,4,0) -> In dienst
A62: Onregelmatigheden | B62: 4764 | C62: =VLOOKUP(B62,chauffeurslijst!A:B,2,0) -> Beke Erik | D62: 43068 | E62: gesprek MF - SH nav regelmatig op reserves de laatste rit niet rijden zonder ok van dispatching; puntering aangepast op 3 dagen (3/10, 15/10, 20/10); laatste verwittiging, volgend voorval ontslag | F62: =MONTH(D62) -> 11 | G62: =YEAR(D62) -> 2017 | H62: =COUNTIF(B:B,B62) -> 24 | I62: =VLOOKUP(B62,'controle 2022'!A:D,4,0) -> In dienst
A63: Algemeen functioneren | B63: 4764 | C63: =VLOOKUP(B63,chauffeurslijst!A:B,2,0) -> Beke Erik | D63: 43251 | E63: sw : Gesprek MF over eigen interpretatie uitvoeren ritten en opvolgen richtlijnen dispatching | F63: =MONTH(D63) -> 5 | G63: =YEAR(D63) -> 2018 | H63: =COUNTIF(B:B,B63) -> 24 | I63: =VLOOKUP(B63,'controle 2022'!A:D,4,0) -> In dienst
A64: Informeel gesprek | B64: 4764 | C64: =VLOOKUP(B64,chauffeurslijst!A:B,2,0) -> Beke Erik | D64: 43720 | E64: Bart VDB: kort gesprek tgv. Melding nav. kwaliteitscontrole: Niet opvolgen van opdrachten, onbetamelijk slecht gedrag, onbeleefd tov. Collega's. Zint chauffeur niet dat hij opgehouden wordt door vaststelingen nav. reizigerscontrole (non verbale comm.: Zuchten, armgebaren, verbaal: klagen, "i/h maken van meldingen zijn jullie goed"). Reactie Erik: vind dat hij niets verkeerd heeft gedaan...storm in glas water. Begrip getoond nav. reeds vertraging dr rijden in omleiding, DOCH steeds respectvol met elkaar omgaan, professioneel blijven, iedereen zijn werk laten doen, zaken anders verwoorden. | F64: =MONTH(D64) -> 9 | G64: =YEAR(D64) -> 2019 | H64: =COUNTIF(B:B,B64) -> 24 | I64: =VLOOKUP(B64,'controle 2022'!A:D,4,0) -> In dienst
A65: Informeel Retibo | B65: 4764 | C65: =VLOOKUP(B65,chauffeurslijst!A:B,2,0) -> Beke Erik | D65: 43839 | E65: Bart VDB gesprek met Erik, opgezocht te Driedeek nav. 1) aanmeldingen Retibo (kunnen beter: slechts 70% succesvol)…hij erkende dikwijls niet aan te loggen…zijn uitleg: omdat ze ons zouden kunnen controleren zekerst…ontkracht met werkelijk doel Retibo-aanmelding: doorsturen realtime information reiziger. Belooft dit in de toekomst steeds te doen. 2) KR binnengekomen fietser rakelings gepasseerd Hagelandkaai (21/11/19), onveilig...gaf terug uitleg onder mom van "is niet mogelijk want wij kunnen daar niet rakelings passeren omdat links van busbaan rijvak ligt voor regulier verkeer", slaat op niets. Heb het gevoel dat hij de schuld altijd bij een ander probeert te leggen. Vriendelijk verzocht steeds rekening te houden met zwakke weggebruiker in het algemeen en verplichte afstand aan te houden. 3) Onze Schadedienst vraagt hem al geruime tijd om ingevuld EAF nav. aanrijding te Dampoort (5/10/19) met vermoedelijke betrokkenheid. Ik heb hem als TC hier al over aangesproken i/h verleden schadedienst te informeren. Erik zegt niets af te weten van incident en dus niet betrokken te zijn...hij zou al 2 mails gestuurd hebben met zijn verhaal (TC in cc) MAAR deze zouden telkens onbestelbaar zijn en niet toekomen. Ik vermoed dat hij zwanst. Hij ging het nogmaals proberen... | F65: =MONTH(D65) -> 1 | G65: =YEAR(D65) -> 2020 | H65: =COUNTIF(B:B,B65) -> 24 | I65: =VLOOKUP(B65,'controle 2022'!A:D,4,0) -> In dienst
... A70: informeel ziekte | B70: 4764 | C70: =VLOOKUP(B70,chauffeurslijst!A:B,2,0) -> Beke Erik | D70: 44792 | E70: tel LVV : aflos aan Mariakerke door pijn op de borst. Weggevoerd met 112. Ernstige verwittiging gehad aan het hart. Moet op 22/08 om 15u30 naar zijn specialist om bijkomende onderzoeken te laten doen. Hij zal ons verwittigen van zodra hij meer weet. | F70: =MONTH(D70) -> 8 | G70: =YEAR(D70) -> 2022 | H70: =COUNTIF(B:B,B70) -> 24 | I70: =VLOOKUP(B70,'controle 2022'!A:D,4,0) -> In dienst
A71: Roken: informeel | B71: 4764 | C71: =VLOOKUP(B70,chauffeurslijst!A:B,2,0) -> Beke Erik | D71: 44861 | E71: Vandaag had ik (TC Bart) wat voor met Erik ..ik wandelde samen met Ali Tayefeh naar zijn bus. Erik was einde dienst en was nog zijn boeltje aan het pakken om zijn bus te verlaten met een aangestoken sigaret in de mond. Net toen ik opstapte, stapte hij enkele seconden later af. Voorkant bus stonk naar de rook...Ik sprak hem aan met de enige boodschap dat het niet de bedoeling is van de sigaret reeds aan te steken op het voertuig. Ik kreeg niet veel praat terug en non communicatief zag ik dat het hem niet wreed aanstond dat ik de opmerking maakte. Ikzelf ga hier niet veel drama van maken maar strikt genomen zou ik hierrond een VVF kunnen opmaken als voormalig controleur en destijds beëdigde persoon. Zelf wil ik natuurlijk ook niet de beuzak zijn .. Toppunt van al is dat Ali al vroeger was opgestapt en Erik ingelicht had dat ik er aan kwam ...dan vind ik zoiets wel lachen in mijn gezicht op een manier. Erik geeft zich in gesprekken bij mij altijd uit als chauffeur met de juiste waarden en normen...maar zelf heb ik het gevoel dat het hem toch allemaal niet veel meer kan schelen... | F71: =MONTH(D71) -> 10 | G71: =YEAR(D71) -> 2022 | H71: =COUNTIF(B:B,B71) -> 24 | I71: =VLOOKUP(B71,'controle 2022'!A:D,4,0) -> In dienst
A72: Roken: informeel | B72: 4764 | C72: =VLOOKUP(B71,chauffeurslijst!A:B,2,0) -> Beke Erik | D72: 44951 | E72: Bjorn contacteert mij dat hij op een paar dagen tijd Erik 2 keer gezien heeft met een brandende sigaret in zijn mond, net voor hij zijn voertuig verlaat. Afgelopen zondag 22/01/2023 en vandaag 25/01/2023. Bjorn heeft hem hier niet over aangesproken MAAR vraagt me hem hieromtrent als TC aan te spreken. Met de boodschap bij volgende inbreuk gezien door één van ons er onherroepelijk een VWF volgt. Wetende dat ik hem op 27/10 ook coachend heb aangesproken en een VWF had kunnen schrijven, kon deze 3de keer zijn C-4 betekenen! Na zijn dienst vandaag contacteer ik Erik met een 2 delige boodschap: EZ vandaag pos. coaching binnengkomen van Erik (Ward De Smet), waarvoor proficiat, AZ gedaan met het door de vingers zien rookbeleid... | F72: =MONTH(D72) -> 1 | G72: =YEAR(D72) -> 2023 | H72: =COUNTIF(B:B,B72) -> 24 | I72: =VLOOKUP(B72,'controle 2022'!A:D,4,0) -> In dienst
A73: Ziekteverzuim | B73: 4764 | C73: =VLOOKUP(B72,chauffeurslijst!A:B,2,0) -> Beke Erik | D73: 45957 | E73: Bart VDB nav. 5 periodes laatste 12 maanden. Gn schade, groene eco, telkens heel goede coachingen, gn vroegrijder, weinig meldingen, gn overtredingen, gn echte Kr., melding v. collega chauffeur rond sigaret aansteken op voertuig alvorens stuurpost te verlaten en andere melding van traag rijden en onnodig lang aan halte blijven staan besproken. | F73: =MONTH(D73) -> 10 | G73: =YEAR(D73) -> 2025 | H73: =COUNTIF(B:B,B73) -> 24
A74: Ziekteverzuim: vergadering | B74: 4793 | C74: =VLOOKUP(B74,chauffeurslijst!A:B,2,0) -> De Fré Sandra | D74: 42571 | E74: verg: gesprek regio na volgende ZI | F74: =MONTH(D74) -> 7 | G74: =YEAR(D74) -> 2016 | H74: =COUNTIF(B:B,B74) -> 13 | I74: =VLOOKUP(B74,'controle 2022'!A:D,4,0) -> In dienst
A75: Ziekteverzuim | B75: 4793 | C75: =VLOOKUP(B75,chauffeurslijst!A:B,2,0) -> De Fré Sandra | D75: 42646 | E75: gesprek CR: verder verzuim te verwachten (hernia in hals, 2 hernia's in onderrug, tenniselleboog, allergie op oog,…), maar doet haar best zoveel mogelijk te komen | F75: =MONTH(D75) -> 10 | G75: =YEAR(D75) -> 2016 | H75: =COUNTIF(B:B,B75) -> 13 | I75: =VLOOKUP(B75,'controle 2022'!A:D,4,0) -> In dienst
A76: Ziekteverzuim: vergadering | B76: 4793 | C76: =VLOOKUP(B76,chauffeurslijst!A:B,2,0) -> De Fré Sandra | D76: 42754 | E76: verg: er is verder verzuim te verwachten, 1 periode na gesprek, en 1 AO; opvolgen, zal nog een ingreep moeten ondergaan tgv AO | F76: =MONTH(D76) -> 1 | G76: =YEAR(D76) -> 2017 | H76: =COUNTIF(B:B,B76) -> 13 | I76: =VLOOKUP(B76,'controle 2022'!A:D,4,0) -> In dienst
A77: Mesor | B77: 4793 | C77: =VLOOKUP(B77,chauffeurslijst!A:B,2,0) -> De Fré Sandra | D77: 43189 | E77: enkel tram vanaf 30/03 tem 31/05 | F77: =MONTH(D77) -> 3 | G77: =YEAR(D77) -> 2018 | H77: =COUNTIF(B:B,B77) -> 13 | I77: =VLOOKUP(B77,'controle 2022'!A:D,4,0) -> In dienst
A78: Mesor | B78: 4793 | C78: =VLOOKUP(B78,chauffeurslijst!A:B,2,0) -> De Fré Sandra | D78: 43242 | E78: enkel tram verlengd tem 30/06 | F78: =MONTH(D78) -> 5 | G78: =YEAR(D78) -> 2018 | H78: =COUNTIF(B:B,B78) -> 13 | I78: =VLOOKUP(B78,'controle 2022'!A:D,4,0) -> In dienst
A79: Ziekteverzuim: vergadering | B79: 4793 | C79: =VLOOKUP(B79,chauffeurslijst!A:B,2,0) -> De Fré Sandra | D79: 43278 | E79: verg: hernia's, laatste periode wegens AO, nu aan het werk, opvolgen | F79: =MONTH(D79) -> 6 | G79: =YEAR(D79) -> 2018 | H79: =COUNTIF(B:B,B79) -> 13 | I79: =VLOOKUP(B79,'controle 2022'!A:D,4,0) -> In dienst
A80: Mesor | B80: 4793 | C80: =VLOOKUP(B80,chauffeurslijst!A:B,2,0) -> De Fré Sandra | D80: 43279 | E80: gedurende twee maanden bij voorkeur max 1 busdienst per week | F80: =MONTH(D80) -> 6 | G80: =YEAR(D80) -> 2018 | H80: =COUNTIF(B:B,B80) -> 13 | I80: =VLOOKUP(B80,'controle 2022'!A:D,4,0) -> In dienst
A81: Mesor | B81: 4793 | C81: =VLOOKUP(B81,chauffeurslijst!A:B,2,0) -> De Fré Sandra | D81: 43329 | E81: verlenging mesor tot eind oktober | F81: =MONTH(D81) -> 8 | G81: =YEAR(D81) -> 2018 | H81: =COUNTIF(B:B,B81) -> 13 | I81: =VLOOKUP(B81,'controle 2022'!A:D,4,0) -> In dienst
A82: Mesor | B82: 4793 | C82: =VLOOKUP(B82,chauffeurslijst!A:B,2,0) -> De Fré Sandra | D82: 43448 | E82: geen verlenging na 01/01/19, vraagt om tramdiensten te kunnen krijgen op de dagen waar de X en T's verzet zijn naar het weekend, maar kan niet gegarandeerd worden (toch niet buiten mesor) | F82: =MONTH(D82) -> 12 | G82: =YEAR(D82) -> 2018 | H82: =COUNTIF(B:B,B82) -> 13 | I82: =VLOOKUP(B82,'controle 2022'!A:D,4,0) -> In dienst
A83: Mesor | B83: 4793 | C83: =VLOOKUP(B83,chauffeurslijst!A:B,2,0) -> De Fré Sandra | D83: 43461 | E83: verlenging mesor : max 2 busdiensten per week, tot 18/02/19 | F83: =MONTH(D83) -> 12 | G83: =YEAR(D83) -> 2018 | H83: =COUNTIF(B:B,B83) -> 13 | I83: =VLOOKUP(B83,'controle 2022'!A:D,4,0) -> In dienst
A84: informeel ziekte | B84: 4793 | C84: =VLOOKUP(B84,chauffeurslijst!A:B,2,0) -> De Fré Sandra | D84: 43802 | E84: LVV : herneemt op 09/12/19 | F84: =MONTH(D84) -> 12 | G84: =YEAR(D84) -> 2019 | H84: =COUNTIF(B:B,B84) -> 13 | I84: =VLOOKUP(B84,'controle 2022'!A:D,4,0) -> In dienst
B85: 4793 | C85: =VLOOKUP(B85,chauffeurslijst!A:B,2,0) -> De Fré Sandra | D85: 44308 | E85: telefoon gekregen van Sandra dat haar zoon gisteren overleden is | F85: =MONTH(D85) -> 4 | G85: =YEAR(D85) -> 2021 | H85: =COUNTIF(B:B,B85) -> 13 | I85: =VLOOKUP(B85,'controle 2022'!A:D,4,0) -> In dienst
A86: snelheid Poperingestraat | B86: 4793 | C86: De Fré Sandra | D86: 45874 | E86: gesprek ED : 2e snelheidsovertreding Poperingestraat bevestigd in een brief dd. 5/8/25 | F86: =MONTH(D86) -> 8 | G86: =YEAR(D86) -> 2025 | H86: =COUNTIF(B:B,B86) -> 13 | I86: =VLOOKUP(B86,'controle 2022'!A:D,4,0) -> In dienst
A87: positieve brief | B87: 4943 | C87: Vervust Guido | D87: 44278 | E87: pos brief globaal dossier 2020 : perfect dossier | F87: =MONTH(D87) -> 3 | G87: =YEAR(D87) -> 2021 | H87: =COUNTIF(B:B,B87) -> 1 | I87: =VLOOKUP(B87,'controle 2022'!A:D,4,0) -> In dienst
A88: Vroegrijden | B88: 5061 | C88: De Clercq Peter | D88: 44088 | E88: Gesprek over +50% te vroeg rijden, je zegt door je jarenlange ervaring op dezelfde lijn vlot tot zeer vlot te laveren en daardoor gestaag minuten voor lopt op het geplande schema . Je hebt begrip voor de gevolgen en het effect op de exploitatie en de collega's. Verder onbesproken blad! | F88: =MONTH(D88) -> 9 | G88: =YEAR(D88) -> 2020 | H88: =COUNTIF(B:B,B88) -> 1 | I88: =VLOOKUP(B88,'controle 2022'!A:D,4,0) -> In dienst
A89: evaluatie lijnverantw. | B89: 5063 | C89: Merre Bart | D89: 44699 | E89: gesprek LVV : bart zal opleiding krijgen voor het geven van begel. En lijnverk. En zal deze later ook geven aan de chauffeurs. Zal later nog eens geëvalueerd worden | F89: =MONTH(D89) -> 5 | G89: =YEAR(D89) -> 2022 | H89: =COUNTIF(B:B,B89) -> 2 | I89: =VLOOKUP(B89,'controle 2022'!A:D,4,0) -> In dienst
A90: evaluatie lijnverantw. | B90: 5063 | C90: Merre Bart | D90: 45478 | E90: gesprek LVV : zeer goed dossier, geeft nu ook lijnverkenning en begeleiding, goede evaluatie lijnverantwoordelijke | F90: =MONTH(D90) -> 7 | G90: =YEAR(D90) -> 2024 | H90: =COUNTIF(B:B,B90) -> 2 | I90: =VLOOKUP(B90,'controle 2022'!A:D,4,0) -> In dienst
A91: ziekteverzuim | B91: 5080 | C91: Van Damme Karin | D91: 43924 | E91: tel EV: heeft nekhernia met uitstraling naar arm; verdere onderzoeken | F91: =MONTH(D91) -> 4 | G91: =YEAR(D91) -> 2020 | H91: =COUNTIF(B:B,B91) -> 1 | I91: =VLOOKUP(B91,'controle 2022'!A:D,4,0) -> In dienst
A92: Melding controle | B92: 5559 | C92: =VLOOKUP(B92,chauffeurslijst!A:B,2,0) -> Hoste Tania | D92: 41718 | E92: 20/03/14: opmerking rijstijl, wordt opgevolgd door rijschool | F92: =MONTH(D92) -> 3 | G92: =YEAR(D92) -> 2014 | H92: =COUNTIF(B:B,B92) -> 6 | I92: =VLOOKUP(B92,'controle 2022'!A:D,4,0) -> In dienst
A93: Geldafgifte | B93: 5559 | C93: =VLOOKUP(B93,chauffeurslijst!A:B,2,0) -> Hoste Tania | D93: 41723 | E93: 25/03/14: gebeld omdat de achterstand nogal hoog was, ging het morgen storten, zegt meestal wel ongeveer elke barema te storten, heb ik niet nagegaan, heb gebeld nav het bedrag zelf, ze was zelf verwonderd dat ze zoveel opgehaald had | F93: =MONTH(D93) -> 3 | G93: =YEAR(D93) -> 2014 | H93: =COUNTIF(B:B,B93) -> 6 | I93: =VLOOKUP(B93,'controle 2022'!A:D,4,0) -> In dienst
A94: Geldafgifte | B94: 5559 | C94: =VLOOKUP(B94,chauffeurslijst!A:B,2,0) -> Hoste Tania | D94: 41829 | E94: komt nog vaak boven 100 euro, vooral wegens hoge ontvangsten lijn 1, stort sinds mei 2014 elke barema | F94: =MONTH(D94) -> 7 | G94: =YEAR(D94) -> 2014 | H94: =COUNTIF(B:B,B94) -> 6 | I94: =VLOOKUP(B94,'controle 2022'!A:D,4,0) -> In dienst
A95: Ongevallen/rijstijl | B95: 5559 | C95: =VLOOKUP(B95,chauffeurslijst!A:B,2,0) -> Hoste Tania | D95: 41829 | E95: 09/07/14: gesprek nav coaching 20/06, heeft dit heel neg. opgenomen, houding instructeur zou niet correct geweest zijn | F95: =MONTH(D95) -> 7 | G95: =YEAR(D95) -> 2014 | H95: =COUNTIF(B:B,B95) -> 6 | I95: =VLOOKUP(B95,'controle 2022'!A:D,4,0) -> In dienst
A96: Geldafgifte | B96: 5559 | C96: =VLOOKUP(B96,chauffeurslijst!A:B,2,0) -> Hoste Tania | D96: 42024 | E96: 20/01/15: stort elke barema, vertraging in verwerking stortingen? | F96: =MONTH(D96) -> 1 | G96: =YEAR(D96) -> 2015 | H96: =COUNTIF(B:B,B96) -> 6 | I96: =VLOOKUP(B96,'controle 2022'!A:D,4,0) -> In dienst
A97: vroegrijden | B97: 5559 | C97: Hoste Tania | D97: 44432 | E97: ss: aandacht aan vroegrijden juli = 26% de vorige maanden steeds een zeer goed cijfer | F97: =MONTH(D97) -> 8 | G97: =YEAR(D97) -> 2021 | H97: =COUNTIF(B:B,B97) -> 6 | I97: =VLOOKUP(B97,'controle 2022'!A:D,4,0) -> In dienst
A98: Ziekteverzuim: vergadering | B98: 5573 | C98: =VLOOKUP(B98,chauffeurslijst!A:B,2,0) -> Dhondt Carlos | D98: 41582 | E98: verg 04/11/13: opvolgen | F98: =MONTH(D98) -> 11 | G98: =YEAR(D98) -> 2013 | H98: =COUNTIF(B:B,B98) -> 2 | I98: =VLOOKUP(B98,'controle 2022'!A:D,4,0) -> In dienst
A99: ziekteverzuim | B99: 5573 | C99: Dhondt Carlos | D99: 44158 | E99: gesprek EV: 5 ziekteperiodes voorbije jaar; verklaring voor gegeven; heeft pechjaar achter de rug; verder goed dossier | F99: =MONTH(D99) -> 11 | G99: =YEAR(D99) -> 2020 | H99: =COUNTIF(B:B,B99) -> 2 | I99: =VLOOKUP(B99,'controle 2022'!A:D,4,0) -> In dienst
A100: Onregelmatigheden | B100: 5599 | C100: =VLOOKUP(B100,chauffeurslijst!A:B,2,0) -> Pretel Philippe | D100: 41549 | E100: 02/10/13: te vroeg rijden en prodata goed zetten | F100: =MONTH(D100) -> 10 | G100: =YEAR(D100) -> 2013 | H100: =COUNTIF(B:B,B100) -> 6 | I100: =VLOOKUP(B100,'controle 2022'!A:D,4,0) -> In dienst
A101: Te laat komen | B101: 5599 | C101: =VLOOKUP(B101,chauffeurslijst!A:B,2,0) -> Pretel Philippe | D101: 41549 | E101: 41549 | F101: =MONTH(D101) -> 10 | G101: =YEAR(D101) -> 2013 | H101: =COUNTIF(B:B,B101) -> 6 | I101: =VLOOKUP(B101,'controle 2022'!A:D,4,0) -> In dienst
A102: Te laat komen | B102: 5599 | C102: =VLOOKUP(B102,chauffeurslijst!A:B,2,0) -> Pretel Philippe | D102: 41660 | E102: nazicht 21/01/14: geen nieuwe vvf | F102: =MONTH(D102) -> 1 | G102: =YEAR(D102) -> 2014 | H102: =COUNTIF(B:B,B102) -> 6 | I102: =VLOOKUP(B102,'controle 2022'!A:D,4,0) -> In dienst
A103: Ziekteverzuim: vergadering | B103: 5599 | C103: =VLOOKUP(B103,chauffeurslijst!A:B,2,0) -> Pretel Philippe | D103: 42048 | E103: verg 13/02/15: geen actie | F103: =MONTH(D103) -> 2 | G103: =YEAR(D103) -> 2015 | H103: =COUNTIF(B:B,B103) -> 6 | I103: =VLOOKUP(B103,'controle 2022'!A:D,4,0) -> In dienst
A104: Informeel | B104: 5599 | C104: =VLOOKUP(B104,chauffeurslijst!A:B,2,0) -> Pretel Philippe | D104: 43920 | E104: ss: melding van achtergelaten sigaretenpeuk op de stuurpost die aangetroffen werd op het voertuig waar Philippe mee binnengereden is op 27/03. Is roker maar beweerde dit zeker niet te doen in zijn stuurpost. | F104: =MONTH(D104) -> 3 | G104: =YEAR(D104) -> 2020 | H104: =COUNTIF(B:B,B104) -> 6 | I104: =VLOOKUP(B104,'controle 2022'!A:D,4,0) -> In dienst
...

Sheet controle 2022
A1: PersoneelsNr | B1: Naam | C1: Voornaam | D1: RedenUitDienst
A2: 10067 | B2: Toumi | C2: Sabri | D2: In dienst
A3: 10150 | B3: Vandenbogaerde | C3: Tony | D3: In dienst
A4: 10171 | B4: Robbe | C4: Sofie | D4: Ontslagnemer
A5: 10299 | B5: Batslé | C5: Dieter | D5: In dienst
A6: 10324 | B6: Eggermont | C6: Wim | D6: In dienst
A7: 10326 | B7: Lefebvre | C7: Olivier | D7: In dienst
A8: 10549 | B8: Bogaert | C8: Ivan | D8: Ontslagnemer
A9: 1075 | B9: De Mol | C9: Raphael | D9: (Brug-)pensioen
A10: 10782 | B10: De Kee | C10: Ina | D10: In dienst
A11: 10903 | B11: De Paepe | C11: Jeroen | D11: Mutatie
A12: 11019 | B12: Gevaert | C12: Ignace | D12: (Brug-)pensioen
A13: 11021 | B13: Seeuws | C13: Marnic | D13: In dienst
... A888: 9979 | B888: Loots | C888: Wim | D888: In dienst

Sheet uit dienst
A1: Opvolgen | B1: Dienstnr | C1: Naam | E1: Opmerking | F1: reden uit dienst
A2: Ziekteverzuim | B2: 1814 | C2: Verhamme Andre | E2: verg 05/03/14: geen actie | F2: pensioen
A3: Ziekteverzuim | B3: 2500 | C3: Bastiaen Eric | E3: verg 27/07/15: opvolgen, operatie | F3: pensioen
A4: Ongevallen/rijstijl | B4: 2500 | C4: Bastiaen Eric | D4: 42571 | E4: tweede signaal op korte tijd ivm rijstijl, coaching gevraagd, ook soc dienst ingelicht in kader van vorig signaal van Eric, vermoedelijk iets meer aan de hand | F4: pensioen
A5: Ziekteverzuim | B5: 2651 | C5: Baeten Willy | E5: 08/04/09, | F5: pensioen
A6: Ongevallen/rijstijl | B6: 2920 | C6: Speeckaert Rudy | E6: 24/09/11: dodelijk ongeval Rooigemlaan | F6: pensioen
A7: Geldafgifte | B7: 3134 | C7: Bracke Dirk | E7: 01/08/11: elke barema storten; tel. 31/01/12: blijft met achterstand van 116,15 euro; brief 20/02/12: nog steeds niet in orde, storten tegen 29/02; nazicht kas op 2/08/13: ok | F7: pensioen
A8: Ziekteverzuim | B8: 3141 | C8: Hellebaut Franky | E8: 07/01/09, 15/05/09 (JB), | F8: pensioen
A9: Ziekteverzuim | B9: 3239 | C9: Dewispelaere Jean-Pierre | E9: 13/08/12, | F9: pensioen
A10: Ziekteverzuim | B10: 3240 | C10: Ide Dirk | E10: 30/09/09, 30/11/09 (MF), 21/05/10 (JB), 15/11/10 (JB) | F10: gedwongen mutatie DES
A11: Geldafgifte | B11: 3240 | C11: Ide Dirk | E11: 30/11/09: laatste kans MF; 21/05/10 met JB: niet meer in negatief staan; 15/11/10 met JB: laatste verwittiging, dagelijks storten; 17/02/12: tel., herinnerd aan de afspraken; 28/02/12: herinnerd aan feit dat hij elke dag moet storten; 13/06/12: gedwongen mutatie ipv ontslag(CR +IVC) | F11: gedwongen mutatie DES
A12: Ongevallen/rijstijl | B12: 3240 | C12: Ide Dirk | E12: gesprek SH nav niet gebruikte halterem (2x op korte tijd) | F12: gedwongen mutatie DES
A13: Ongevallen/rijstijl | B13: 3437 | C13: Damoiseaux Marc | E13: 20/11/12: einde opvolging rijschool (pos.) | F13: pensioen
A14: Ziekteverzuim | B14: 3594 | C14: Vanlancker Jean-Pierre | E14: verg 05/03/14: steeds zelfde problematiek | F14: pensioen
A15: Ziekteverzuim: vergadering | B15: 3670 | C15: =VLOOKUP(B15,chauffeurslijst!A:B,2,0) -> Van Geyt Michael | D15: 42048 | E15: verg 13/02/15: chronische problemen, geen beterschap in zicht | F15: pensioen
A16: Ziekteverzuim | B16: 3690 | C16: =VLOOKUP(B16,chauffeurslijst!A:B,2,0) -> Galens Georges | E16: verg 28/07/15: ingreep ondergaan, wil in pensioen gaan gezien zijn toestand | F16: AZV2
A17: Ziekteverzuim | B17: 3690 | C17: =VLOOKUP(B17,chauffeurslijst!A:B,2,0) -> Galens Georges | E17: 07/10/15: Georges kwam langs ikv een eventuele werkhervatting bij de arbeidsgeneesheer, voor ev aangepast werk, maar er is nog geen sprake van werkhervatting. | F17: AZV2
A18: Ziekteverzuim | B18: 3690 | C18: =VLOOKUP(B18,chauffeurslijst!A:B,2,0) -> Galens Georges | D18: 42395 | E18: verg: arbeidsgeneesheer geen voorstander van hervatting | F18: AZV2
A19: Ziekteverzuim | B19: 3690 | C19: =VLOOKUP(B19,chauffeurslijst!A:B,2,0) -> Galens Georges | D19: 42583 | E19: verg: hervatten, ook aangepast werk, is weinig waarschijnlijk, ook volgens arbeidsgeneesheer. Vermoedelijk AZV2 vanaf 4/02/2017. | F19: AZV2
A20: Ziekteverzuim | B20: 3690 | C20: =VLOOKUP(B20,chauffeurslijst!A:B,2,0) -> Galens Georges | D20: 42754 | E20: verg: zal op AZV2 gaan op 4 feb 2017, kan niet van ZI op brugpensioen (nek - evenwichtsstoornissen) | F20: AZV2
A21: Ziekteverzuim | B21: 3744 | C21: D'Hertoghe Luc | E21: verg 05/03/14: zware problematiek, zal vermoedelijk niet snel terugkomen | F21: overleden
A22: Ziekteverzuim | B22: 3769 | C22: Vandeveire Jean Pierre | E22: 29/08/12, verg 06/05/14: pensioen aangevraagd; 29/09/14 (informeel): last van hernia; | F22: pensioen
A23: Ziekteverzuim | B23: 3769 | C23: Vandeveire Jean Pierre | E23: verg 15/04/15: gaat in pensioen begin 2016, geen actie; | F23: pensioen
A24: Ziekteverzuim | B24: 3769 | C24: Vandeveire Jean Pierre | E24: verg 27/07/15: geen actie | F24: pensioen
A25: Ziekteverzuim | B25: 3780 | C25: Van Eeghem Martin | E25: verg 05/03/14: geen actie | F25: pensioen
A26: Ziekteverzuim | B26: 3860 | C26: Verschraegen Daniël | E26: 17/01/12, verg 04/11/13: sociale dienst neemt contact op, verg 05/03/14: patroon zal blijven, nog eens apart te bespreken; verg 06/05/14: gesprek CR op 07/05/14, brugpensioen suggereren; 07/05/14; | F26: kasdienst en pensioen
A27: Te laat komen | B27: 3860 | C27: Verschraegen Daniël | E27: 17/01/12; nazicht 21/01/14: 6 nieuwe vvf, 2 in 2012 en 4 in 2013; 07/05/14; 27/11/14 (slaapt slecht door pijn) | F27: kasdienst en pensioen
A28: Ziekteverzuim | B28: 3860 | C28: Verschraegen Daniël | E28: verg 27/07/15: brugpensioen aangevraagd, werkt 100%, helpt niet voor zijn periodes | F28: kasdienst en pensioen
A29: Ziekteverzuim | B29: 3860 | C29: Verschraegen Daniël | D29: 42395 | E29: verg: via mesor voorstel voor 3e job, zal vanaf juni naar magazijn of elders kunnen om dan in brugpensioen te kunnen gaan, vermoedelijk ziek tot aangepast werk | F29: kasdienst en pensioen
A30: Ziekteverzuim | B30: 3948 | C30: Lagae Rudi | E30: 12/02/10, 02/10/12, 20/03/13 (3 nieuwe periodes na vorig gesprek, waarvan 1 AO), langdurige periode na gesprek: 10/05/13 tot 26/07/13; verg 04/11/13: sociale dienst neemt contact; verg 05/03/14: dossier voorbereiden; verg 06/05/14: gesprek IVC; 04/07/14 (IVC + CR): vermoedelijk nog operatie nodig (knieprothese), moet bij herneming goed dossier worden en blijven; 24/12/14: mailtje gestuurd met vraag hoe het is; | F30: aangepast werk en nadien brugpensioen
A31: Ziekteverzuim | B31: 3948 | C31: Lagae Rudi | E31: 02/01/15: antwoord: verlenging; | F31: aangepast werk en nadien brugpensioen
A32: Ziekteverzuim | B32: 3948 | C32: Lagae Rudi | E32: verg 13/02/15: nog niet hernomen, opvolgen; | F32: aangepast werk en nadien brugpensioen
A33: Ziekteverzuim | B33: 3948 | C33: Lagae Rudi | E33: verg 28/07/15: opvolgen, pensioen aangevraagd? | F33: aangepast werk en nadien brugpensioen
A34: Geldafgifte | B34: 3948 | C34: Lagae Rudi | E34: 02/10/12: elke barema storten, 20/03/13: stort elke barema, nazicht kas 2/08/13: openstaand saldo, al een tijdje ziek, ok voor brief; 04/07/14 (IVC + CR): vermoedelijk nog operatie nodig (knieprothese), moet bij herneming goed dossier worden en blijven | F34: aangepast werk en nadien brugpensioen
A35: Te laat komen | B35: 3948 | C35: Lagae Rudi | E35: 02/10/12, 20/03/13: na vorig gesprek 2x te laat gekomen, waarvan 1 door misverstand met verwisseling, kijkt nu op website; nazicht 21/01/14: 2 nieuwe vvf; 04/07/14 (IVC + CR): vermoedelijk nog operatie nodig (knieprothese), moet bij herneming goed dossier worden en blijven | F35: aangepast werk en nadien brugpensioen
A36: Onregelmatigheden | B36: 3964 | C36: Vaneeckhaute Philippe | E36: 12/11/14: nav verkoop ticketten op voertuig | F36: pensioen
A37: Ziekteverzuim | B37: 3986 | C37: =VLOOKUP(B37,chauffeurslijst!A:B,2,0) -> Decaluwe Dirk | E37: 20/10/09, 08/03/10; | F37: pensioen
A38: Te laat komen | B38: 3986 | C38: =VLOOKUP(B38,chauffeurslijst!A:B,2,0) -> Decaluwe Dirk | E38: 26/05/14: niet op gesprek gekomen, brief gestuurd | F38: pensioen
A39: Ziekteverzuim | B39: 3986 | C39: =VLOOKUP(B39,chauffeurslijst!A:B,2,0) -> Decaluwe Dirk | E39: verg 15/04/15: geen actie; | F39: pensioen
A40: Ziekteverzuim | B40: 3986 | C40: =VLOOKUP(B40,chauffeurslijst!A:B,2,0) -> Decaluwe Dirk | E40: verg 27/07/15: geen actie | F40: pensioen
A41: Ziekteverzuim | B41: 3986 | C41: =VLOOKUP(B41,chauffeurslijst!A:B,2,0) -> Decaluwe Dirk | D41: 42583 | E41: verg: P40 aangevraagd, attest tot eind september, zal missch in september wel naar die rol kunnen overgaan | F41: pensioen
A42: Ziekteverzuim | B42: 3986 | C42: =VLOOKUP(B42,chauffeurslijst!A:B,2,0) -> Decaluwe Dirk | D42: 42618 | E42: vanaf 01/09 in P40 | F42: pensioen
A43: Ziekteverzuim | B43: 4028 | C43: Vanhalst Carlo | E43: 10/03/10, | F43: pensioen
A44: Geldafgifte | B44: 4028 | C44: Vanhalst Carlo | E44: tel. 10/11/14 (cr): 49 euro die gestort is op 11/10 zit niet in AS400, doet nazicht; klopt, zal de 49 euro storten | F44: pensioen
A45: Geldafgifte | B45: 4042 | C45: Vermeire Lucas | E45: opvolgen na herneming ziekte; controle 05/08/13: kan beter | F45: pensioen
A46: Ziekteverzuim | B46: 4048 | C46: De Mol Oscar | E46: heeft nog niet gewerkt sinds hij terug bij E gekomen is op 01/05/12 | F46: ontslag
A47: Ziekteverzuim | B47: 4049 | C47: Reyniers Patrick | E47: verg 05/03/14: geen actie | F47: pensioen
A48: Ziekteverzuim | B48: 4053 | C48: Francois Roland | E48: verg 13/02/15: geen actie | F48: pensioen
A49: Onregelmatigheden | B49: 4053 | C49: Francois Roland | E49: 02/04/14: gebeld nav melding door collega's dat hij wildplast aan Melle Leeuw, ontkent dit | F49: pensioen
A50: Ziekteverzuim | B50: 4056 | C50: Gregoir Edgard | E50: verg 06/01/16: binnenkort pensioen | F50: pensioen
A51: Ziekteverzuim: vergadering | B51: 4064 | C51: =VLOOKUP(B51,chauffeurslijst!A:B,2,0) -> Graton Philippe | D51: 42375 | E51: verg 06/01/16: soc dienst neemt contact op | F51: pensioen
A52: Ziekteverzuim: vergadering | B52: 4064 | C52: =VLOOKUP(B52,chauffeurslijst!A:B,2,0) -> Graton Philippe | D52: 42571 | E52: verg: zou in herfstvakantie willen hernemen na LZ, 80% via resterende verlofdagen | F52: pensioen
A53: Ziekteverzuim: vergadering | B53: 4064 | C53: =VLOOKUP(B53,chauffeurslijst!A:B,2,0) -> Graton Philippe | D53: 42626 | E53: verg: geen evolutie, na herneming kort opvolgen (houding naar oversten niet altijd ok) | F53: pensioen
A54: Ziekteverzuim: informeel | B54: 4064 | C54: =VLOOKUP(B54,chauffeurslijst!A:B,2,0) -> Graton Philippe | D54: 42669 | E54: mag niet hernemen van arbeidsgeneesheer, is langsgekomen bij SW: nu medische probl | F54: pensioen
A55: Ziekteverzuim | B55: 4064 | C55: =VLOOKUP(B55,chauffeurslijst!A:B,2,0) -> Graton Philippe | D55: 42845 | E55: sw : Filip kwam op eigen initiatief langs voor een gesprek, is momenteel terug aan het werk maar heeft nu al weet van 2 medische problemen waarvoor hij terug even uit zal zijn. Hij vreest voor ontslag, Filip wenst op brugpensioen te gaan (kan in principe vanaf 08/2018) | F55: pensioen
A56: Ziekteverzuim: informeel | B56: 4064 | C56: =VLOOKUP(B56,chauffeurslijst!A:B,2,0) -> Graton Philippe | D56: 43084 | E56: opgemerkt dat Philippe thuis is sinds 24/11, verlenging tot 31/12; info planning: aan ogen geopereerd, complicaties opgetreden, daardoor langer thuis dan voorzien | F56: pensioen
A57: Ziekteverzuim: informeel | B57: 4064 | C57: =VLOOKUP(B57,chauffeurslijst!A:B,2,0) -> Graton Philippe | D57: 43117 | E57: mail soc dienst: "Philippe houdt me om de twee weken op de hoogte van zijn ziektetoestand. Hij is hier vandaag geweest, ik mocht van hem jullie op de hoogte brengen van de medische situatie. Philippe heeft Katarakt en is hiervoor geopereerd. Na de operatie zijn er wat complicaties opgedoken, waardoor hij alles dubbel ziet en draait. Hij is een second opinion gaan halen bij een dokter in het UZ. Deze dokter schrijft hem opnieuw een operatie voor en daarnaast ook nog een lens. Op 30 januari 2018 krijgt hij een afspraak wanneer de operatie kan gebeuren op het rechter oog. Hij is terug naar de eerste dokter geweest om vroeger te kunnen behandeld worden en kreeg daar nu ook een testlens voorgeschreven. Deze zou deze week moeten binnen zijn, zodat de testfase voor het ene oog kan starten. Ik zie Philippe niet eerder dan eind februari terugkomen. Ik heb hem wel op de planning gezet van 22 februari 2018 bij dr. Berlengéé voor een checkup en stand van zaken. | F57: pensioen
A58: Ziekteverzuim: informeel | B58: 4064 | C58: =VLOOKUP(B58,chauffeurslijst!A:B,2,0) -> Graton Philippe | D58: 43136 | E58: cr: tel contact; oog wordt volgende week geopereerd, hoopt erna snel te kunnen komen werken (kan zelfs met bril niet rijden want ziet dubbel) | F58: pensioen
A59: Ziekteverzuim: informeel | B59: 4064 | C59: =VLOOKUP(B59,chauffeurslijst!A:B,2,0) -> Graton Philippe | D59: 43144 | E59: soc dienst: Deze voormiddag contact opgenomen met Philippe Graton. Hij liet weten dat zijn medische toestand gunstig evolueert. Ik had hem een afspraak gegeven bij de arbeidsgeneesheer op 22/02 en deze gaat doorgaan. Hij voorziet een volledige hervatting (binnen zijn normaal 80% regime). | F59: pensioen
A60: Ziekteverzuim: informeel | B60: 4064 | C60: =VLOOKUP(B60,chauffeurslijst!A:B,2,0) -> Graton Philippe | D60: 43153 | E60: mag hernemen vanaf 01/03 | F60: pensioen
A61: Ziekteverzuim: vergadering | B61: 4064 | C61: =VLOOKUP(B61,chauffeurslijst!A:B,2,0) -> Graton Philippe | D61: 43278 | E61: verg: gaat in brugpensioen dit jaar | F61: pensioen
A62: Ongevallen/rijstijl | B62: 4092 | C62: Leman Willy | E62: 20/06/12: ongevallenpreventie | F62: pensioen
A63: Geldafgifte | B63: 4116 | C63: De Schuyter Donald | F63: overleden
A64: Ziekteverzuim | B64: 4151 | C64: D'Hont Rudi | E64: verg 05/03/14: geen actie | F64: pensioen
A65: Ziekteverzuim | B65: 4201 | C65: Carlier Patrick | F65: AZV2
A66: Ziekteverzuim | B66: 4212 | C66: Van Brantheghem Marc | E66: 05/06/09, verg 04/11/13: aangepast werk tot pensioen aug '14 | F66: pensioen
A67: Ziekteverzuim | B67: 4238 | C67: Maes Suzanne | E67: gesprek IVC + CR 04/10/13: binnen 6md opnieuw evalueren, verg 05/03/14: zie afspraken gesprek 04/10; 28/04/14 (IVC+CR): geen verbetering, laten overgaan naar AZV2; verg 13/02/15: geen actie | F67: AZV2
A68: Ziekteverzuim | B68: 4520 | C68: Bekaert Martin | E68: 24/12/14: LZ, kanker; | F68: overleden
A69: Ziekteverzuim | B69: 4520 | C69: Bekaert Martin | E69: verg 13/02/15: geen actie, wordt geopereerd in maart; verg 28/07/15: geen actie | F69: overleden
A70: Ziekteverzuim | B70: 4520 | C70: Bekaert Martin | E70: 18/08/15: heeft gebeld, had een aantal vragen over invaliditeit, progr werken, enz. verwezen naar soc dienst | F70: overleden
A71: Te laat komen | B71: 4520 | C71: Bekaert Martin | E71: 14/04/14; | F71: overleden
A72: Ongevallen/rijstijl | B72: 4596 | C72: Savoye Jacques | E72: 14/06/12: ongevallenpreventie; 20/11/12: einde opvolging rijschool (pos.; schreef voor alles een verslag zoals het hoort) | F72: pensioen
A73: Ziekteverzuim | B73: 4965 | C73: Vanderhaegen Vera | E73: 21/10/11, verg 04/11/13: ok | F73: AZV2
A74: Ziekteverzuim | B74: 5289 | C74: Helderweirt Eddy | E74: 26/03/10, 08/08/12, 10/07/13, verg 04/11/13: ok; tel 28/01/14: is in nov '13 ziek geweest tgv slechte bestuurderszetel bus 3384 (iets in rug geschoten); tel 20/02/14: kon GV niet bereiken (is in verlof), moest zijn ei kwijt ivm problemen met zijn dochter, vroeg me of hij even thuis mocht blijven. Ik heb gezegd dat hij dat voor zichzelf moet beslissen, maar ook dat ziekte zwaarder weegt in een dossier dan verlof. Maar als het niet gaat, moet hij thuisblijven. | F74: ontslag
A75: Geldafgifte | B75: 5289 | C75: Helderweirt Eddy | E75: tel 28/01/14: heeft van kas brief gekregen ivm meeslepend saldo van 18,70 euro, weet niet waar dit vandaan komt, houdt alles bij en volgens hem is alles ok; de raad gegeven met KV contact op te nemen en te vragen naar een overzicht waar dit vandaan komt; tel 31/01/14: fout ligt bij Eddy zelf, afgelopen zomer zich vergist, komt vandaag in orde | F75: ontslag
A76: Ziekteverzuim | B76: 5289 | C76: Helderweirt Eddy | D76: 42571 | E76: verg: opvolgen | F76: ontslag
A77: Ziekteverzuim | B77: 5289 | C77: Helderweirt Eddy | D77: 42754 | E77: verg: ZI tot eind maart, heeft aangepast werk bij M; geeft aan dat hij niet wil terugkomen als chauffeur; er was eerder gezegd dat hij in maart moest beginnen als chauffeur, nu verlenging tot eind maart; gesprek IVC: hernemen als chauffeur in april of ontslag | F77: ontslag
A78: Ziekteverzuim | B78: 5289 | C78: Helderweirt Eddy | D78: 42803 | E78: info SH: 13/03 afspraak met IVC en Eddy met de bedoeling hem weer aan het werk te krijgen | F78: ontslag
A79: Geldafgifte | B79: 6266 | C79: =VLOOKUP(B79,chauffeurslijst!A:B,2,0) -> Delmeiren Marnic | E79: 26/11/09: elke barema storten; nazicht kas 02/08/13: ok; 25/03/14: hem gebeld omdat hij de laatste tijd vaak boven 100 euro kwam, stort wel regelmatig; tel. 02/10/14 (cr), springt morgen eens binnen, zou nu ok moeten zijn | F79: lijncontroleur geworden
A80: Geldafgifte | B80: 6266 | C80: =VLOOKUP(B80,chauffeurslijst!A:B,2,0) -> Delmeiren Marnic | E80: 18/12/2015 : bedrag opgelopen door onzorgvuldigheid, alees gestort op datum vangesprek | F80: lijncontroleur geworden
A81: Te laat komen | B81: 6266 | C81: =VLOOKUP(B81,chauffeurslijst!A:B,2,0) -> Delmeiren Marnic | D81: 42633 | E81: SW: paar keer te laat door kleinigheden, duidelijk een samenloop van omstandigheden. Prima dossier | F81: lijncontroleur geworden
A82: Ziekteverzuim | B82: 7631 | C82: De Rijcke Ronald | E82: 14/03/11, verg 04/11/13: opvolgen | F82: pensioen
A83: Ziekteverzuim | B83: 7896 | C83: Penning Guy | E83: 30/09/14: melding soc dienst, ZH vanaf 27/10 (operatie); | F83: AZV2
A84: Ziekteverzuim | B84: 7896 | C84: Penning Guy | E84: verg 13/02/15: gesprek CR na herneming; | F84: AZV2
A85: Ziekteverzuim | B85: 7896 | C85: Penning Guy | E85: verg 28/07/15: operatie mislukt, geen actie | F85: AZV2
A86: Ziekteverzuim | B86: 7896 | C86: Penning Guy | D86: 42395 | E86: verg: soc dienst neemt contact op | F86: AZV2
A87: Ziekteverzuim | B87: 7896 | C87: Penning Guy | D87: 42583 | E87: verg: werkt 50%, en Guy wil dit niet in belbus, ons aanvoelen is hem niet op AZV2 te laten gaan (IVC probeert nog eens bij Guy Van Haute, anders mogelijk ontslag) - dossier opmaken en gesprek plannen begin september | F87: AZV2
A88: Ziekteverzuim | B88: 7902 | C88: =VLOOKUP(B88,chauffeurslijst!A:B,2,0) -> Cornelis Dirk | D88: 41213 | E88: 41213 | F88: pensioen
A89: Ziekteverzuim: informeel | B89: 7902 | C89: =VLOOKUP(B89,chauffeurslijst!A:B,2,0) -> Cornelis Dirk | D89: 41662 | E89: melding dat hij in de put zit wegens opname vrouw, kan niet komen werken, wil contact met soc dienst -> doorverwezen | F89: pensioen
A90: Ziekteverzuim: informeel | B90: 7902 | C90: =VLOOKUP(B90,chauffeurslijst!A:B,2,0) -> Cornelis Dirk | D90: 41710 | E90: weer problemen met vrouw (alc), zal weekje ziek zijn, gezegd dat dit natuurlijk geen jaren kan aanslepen | F90: pensioen
A91: Ziekteverzuim: informeel | B91: 7902 | C91: =VLOOKUP(B91,chauffeurslijst!A:B,2,0) -> Cornelis Dirk | D91: 41901 | E91: binnengekomen, moet geopereerd worden aan het hart, zat er mee in om job te verliezen | F91: pensioen
A92: Ziekteverzuim: vergadering | B92: 7902 | C92: =VLOOKUP(B92,chauffeurslijst!A:B,2,0) -> Cornelis Dirk | D92: 42048 | E92: verg 13/02/15: aan het revalideren, bij terugkomst gesprek regio, boodschap dat het kritisch wordt | F92: pensioen
A93: Ziekteverzuim: vergadering | B93: 7902 | C93: =VLOOKUP(B93,chauffeurslijst!A:B,2,0) -> Cornelis Dirk | D93: 42213 | E93: verg 28/07/15: hartoperatie gehad, geen actie | F93: pensioen
A94: Ziekteverzuim: informeel | B94: 7902 | C94: =VLOOKUP(B94,chauffeurslijst!A:B,2,0) -> Cornelis Dirk | D94: 42226 | E94: 10/08/15: informeel gesproken in de gang, voelt zich veel beter nu hij aan zee woont | F94: pensioen
A95: Ziekteverzuim: informeel | B95: 7902 | C95: =VLOOKUP(B95,chauffeurslijst!A:B,2,0) -> Cornelis Dirk | D95: 42870 | E95: cr: gebeld, heeft last van hernia in de nek, heeft deze week afspraak voor tweede epidurale, heeft vernomen dat er 3 nodig zouden zijn, wil deze zo snel mogelijk want wil in brugpensioen kunnen gaan | F95: pensioen
A96: Ziekteverzuim: vergadering | B96: 7902 | C96: =VLOOKUP(B96,chauffeurslijst!A:B,2,0) -> Cornelis Dirk | D96: 42895 | E96: overleg met soc dienst: geen actie | F96: pensioen
A97: Ziekteverzuim: vergadering | B97: 7902 | C97: =VLOOKUP(B97,chauffeurslijst!A:B,2,0) -> Cornelis Dirk | D97: 42984 | E97: verg: wacht SWT af, momenteel aan het werk | F97: pensioen
A98: Ziekteverzuim | B98: 7965 | C98: Batselaere Jean-Claude | E98: 16/05/13 (tijdens evaluatiegesprek LV); verg 04/11/13: opvolgen; | F98: brugpensioen
A99: Ziekteverzuim | B99: 7965 | C99: Batselaere Jean-Claude | E99: verg 13/02/15: geen actie; | F99: brugpensioen
A100: Ziekteverzuim | B100: 7965 | C100: Batselaere Jean-Claude | E100: verg 27/07/15: AO + 1 korte ZI, opvolgen | F100: brugpensioen
...

Sheet statistiek
A1: Jaar | B1: 2018
A3: Aantal van Onderwerp | B3: Kolomlabels
A4: Rijlabels | B4: 1 | C4: 2 | D4: 3 | E4: 4 | F4: 5 | G4: 6 | H4: 7 | I4: 8 | J4: 9 | K4: 12 | L4: Eindtotaal
A5: Ziekteverzuim: vergadering | B5: 15 | C5: 10 | F5: 1 | G5: 114 | H5: 1 | J5: 2 | L5: 143
A6: Ziekteverzuim: informeel | B6: 11 | C6: 21 | D6: 25 | E6: 20 | F6: 12 | G6: 8 | H6: 21 | I6: 11 | J6: 1 | L6: 130
A7: Ziekteverzuim | B7: 10 | C7: 7 | D7: 10 | E7: 2 | F7: 2 | G7: 3 | H7: 17 | I7: 4 | J7: 2 | L7: 57
A8: Evaluatiegesprek | B8: 5 | C8: 3 | D8: 5 | E8: 5 | F8: 5 | G8: 1 | H8: 1 | I8: 4 | L8: 29
A9: Mesor | B9: 2 | C9: 1 | D9: 2 | E9: 2 | F9: 5 | G9: 6 | I9: 7 | J9: 1 | K9: 1 | L9: 27
A10: Algemeen functioneren | B10: 5 | C10: 2 | D10: 7 | F10: 3 | G10: 3 | H10: 2 | I10: 2 | J10: 1 | L10: 25
A11: Onregelmatigheden | B11: 2 | C11: 5 | D11: 1 | E11: 1 | F11: 3 | L11: 12
A12: Mondelinge opmerkingen | B12: 4 | C12: 1 | E12: 1 | F12: 2 | G12: 1 | H12: 1 | I12: 1 | J12: 1 | L12: 12
A13: Klantenreacties | B13: 3 | D13: 3 | E13: 3 | G13: 1 | H13: 1 | L13: 11
A14: Ongevallen/rijstijl | B14: 2 | D14: 2 | E14: 2 | F14: 3 | I14: 1 | L14: 10
A15: Geldafgifte | B15: 1 | C15: 2 | D15: 1 | E15: 1 | F15: 1 | I15: 1 | L15: 7
A16: Ziekteverzuim | H16: 3 | I16: 2 | L16: 5
A17: ADM | G17: 2 | I17: 1 | J17: 2 | L17: 5
A18: Informeel | D18: 2 | E18: 2 | L18: 4
A19: Ziekteverzuim | G19: 3 | L19: 3
A20: Opleiding | C20: 2 | L20: 2
A21: Conflict | H21: 1 | I21: 1 | L21: 2
A22: Arbeidsongevallen | E22: 1 | H22: 1 | L22: 2
A23: agressie | I23: 2 | L23: 2
A24: Arbeidsongeval | I24: 1 | L24: 1
A25: Afwezigheid | J25: 1 | L25: 1
A26: Ziekteverzuim / geldafgifte | I26: 1 | L26: 1
A27: Vroegrijden | C27: 1 | L27: 1
A28: Diverse | C28: 1 | L28: 1
A29: Monitoring | H29: 1 | L29: 1
A30: Te laat komen | G30: 1 | L30: 1
A31: Roken | D31: 1 | L31: 1
A32: Eindtotaal | B32: 60 | C32: 56 | D32: 59 | E32: 40 | F32: 37 | G32: 143 | H32: 50 | I32: 39 | J32: 11 | K32: 1 | L32: 496
A33: zonder ZI: verg en zonder mesor | B33: =GETPIVOTDATA("Onderwerp",$A$3,"Maand",1)-GETPIVOTDATA("Onderwerp",$A$3,"Onderwerp","Ziekteverzuim: vergadering","Maand",1)-GETPIVOTDATA("Onderwerp",$A$3,"Onderwerp","Mesor","Maand",1) -> 43 | C33: =GETPIVOTDATA("Onderwerp",$A$3,"Maand",2)-GETPIVOTDATA("Onderwerp",$A$3,"Onderwerp","Ziekteverzuim: informeel","Maand",2)-GETPIVOTDATA("Onderwerp",$A$3,"Onderwerp","Mesor","Maand",2) -> 34 | D33: =GETPIVOTDATA("Onderwerp",$A$3,"Maand",3)-GETPIVOTDATA("Onderwerp",$A$3,"Onderwerp","Mesor","Maand",3) -> 57 | E33: =GETPIVOTDATA("Onderwerp",$A$3,"Maand",4)-GETPIVOTDATA("Onderwerp",$A$3,"Onderwerp","Mesor","Maand",4) -> 38 | F33: =GETPIVOTDATA("Onderwerp",$A$3,"Maand",6)-GETPIVOTDATA("Onderwerp",$A$3,"Onderwerp","Ziekteverzuim: vergadering","Maand",6)-GETPIVOTDATA("Onderwerp",$A$3,"Onderwerp","Mesor","Maand",6) -> 23 | G33: =GETPIVOTDATA("Onderwerp",$A$3,"Maand",2)-GETPIVOTDATA("Onderwerp",$A$3,"Onderwerp","Ziekteverzuim: informeel","Maand",2)-GETPIVOTDATA("Onderwerp",$A$3,"Onderwerp","Mesor","Maand",2) -> 34 | H33: =GETPIVOTDATA("Onderwerp",$A$3,"Maand",7)-GETPIVOTDATA("Onderwerp",$A$3,"Onderwerp","Ziekteverzuim: vergadering","Maand",7) -> 49 | I33: =GETPIVOTDATA("Onderwerp",$A$3,"Maand",8)-GETPIVOTDATA("Onderwerp",$A$3,"Onderwerp","Mesor","Maand",8) -> 32

Sheet chauffeurslijst
A1: PersoneelsNr | B1: Naam
A2: 10067 | B2: Toumi Sabri
A3: 10150 | B3: Vandenbogaerde Tony
A4: 10171 | B4: Robbe Sofie
A5: 10299 | B5: Batslé Dieter
A6: 10324 | B6: Eggermont Wim
A7: 10326 | B7: Lefebvre Olivier
A8: 10549 | B8: Bogaert Ivan
A9: 1075 | B9: De Mol Raphael
A10: 10782 | B10: De Kee Ina
A11: 10903 | B11: De Paepe Jeroen
A12: 11019 | B12: Gevaert Ignace
A13: 11021 | B13: Seeuws Marnic
... A618: 34044 | B618: Wieme Kevin
A619: 34178 | B619: Vanhouteghem Jonas | C619: =VALUE(A619) -> 34178
A620: 34180 | B620: Van den Daele Jan | C620: =VALUE(A620) -> 34180
A621: 34198 | B621: Pelfrene Toby | C621: =VALUE(A621) -> 34198
A622: 34286 | B622: Ghani Mozamil | C622: =VALUE(A622) -> 34286
A623: 34294 | B623: Jagne Momodou | C623: =VALUE(A623) -> 34294
A624: 34312 | B624: Sari Halil | C624: =VALUE(A624) -> 34312
A625: 34313 | B625: Baert Peter | C625: =VALUE(A625) -> 34313
A626: 34325 | B626: Eid Mahammud | C626: =VALUE(A626) -> 34325
A627: 34328 | B627: Kerremans Jürgen | C627: =VALUE(A627) -> 34328
A628: 34351 | B628: Callant Dieter | C628: =VALUE(A628) -> 34351
A629: 34385 | B629: Goossens Wesley | C629: =VALUE(A629) -> 34385
A630: 34445 | B630: Wulleput Illya | C630: =VALUE(A630) -> 34445
... A690: 35670 | B690: Krak Jerry Ruben | C690: =VALUE(A690) -> 35670
A691: 35671 | B691: Verpoest Wesley | C691: 33142
A692: 35709 | B692: El Gasmi Sami
A693: 35714 | B693: Stubbe Jarne
A694: 35753 | B694: Bagseven Mikail
A695: 35761 | B695: Simsek Huseyin
A696: 35786 | B696: Braet Juanito
A697: 35816 | B697: Guyssens Peter
A698: 35850 | B698: Mouton Jim
A699: 35858 | B699: Kalhor Kamran
A700: 35862 | B700: Van Damme Patrick
A701: 35939 | B701: Vermeire Timothy
A702: 3594 | B702: Van Lancker Jean-Pierre
A703: 35962 | B703: Mouhine Marouane
... A888: 9979 | B888: Loots Wim

Sheet Gesprekken 2015
A1: Aard | B1: dienstnr | C1: naam | D1: datum gesprek | E1: met wie | F1: afspraak | G1: jaar
A2: Ziekteverzuim | B2: 29476 | C2: =IF(ISNA(VLOOKUP(B2,chauffeurslijst!A:B,2,0)),"",(VLOOKUP(B2,chauffeurslijst!A:B,2,0))) | D2: 42016 | E2: IVC + CR | F2: ontslag | G2: =YEAR(D2) -> 2015
A3: Ziekteverzuim | B3: 29369 | C3: =IF(ISNA(VLOOKUP(B3,chauffeurslijst!A:B,2,0)),"",(VLOOKUP(B3,chauffeurslijst!A:B,2,0))) -> Vyncke Sissi | D3: 42017 | E3: CR | F3: ingesproken op voice mail dat het zo niet kan blijven duren | G3: =YEAR(D3) -> 2015
A4: Ziekteverzuim | B4: 21426 | C4: =IF(ISNA(VLOOKUP(B4,chauffeurslijst!A:B,2,0)),"",(VLOOKUP(B4,chauffeurslijst!A:B,2,0))) -> Housiaux Yves | D4: 42023 | E4: CR | F4: zelf aangevraagd | G4: =YEAR(D4) -> 2015
A5: Ziekteverzuim | B5: 23881 | C5: =IF(ISNA(VLOOKUP(B5,chauffeurslijst!A:B,2,0)),"",(VLOOKUP(B5,chauffeurslijst!A:B,2,0))) -> Cornette Jurgen | D5: 42023 | E5: IVC + CR | F5: gunstige evaluatie | G5: =YEAR(D5) -> 2015
A6: Ziekteverzuim | B6: 11744 | C6: =IF(ISNA(VLOOKUP(B6,chauffeurslijst!A:B,2,0)),"",(VLOOKUP(B6,chauffeurslijst!A:B,2,0))) -> De Pauw Dorothy | D6: 42023 | E6: IVC + CR | F6: gunstige evaluatie | G6: =YEAR(D6) -> 2015
A7: Ziekteverzuim | B7: 15087 | C7: =IF(ISNA(VLOOKUP(B7,chauffeurslijst!A:B,2,0)),"",(VLOOKUP(B7,chauffeurslijst!A:B,2,0))) -> Kiliç Halil | D7: 42024 | E7: CR | F7: tijdens gesprek TL | G7: =YEAR(D7) -> 2015
A8: Ziekteverzuim | B8: 20479 | C8: =IF(ISNA(VLOOKUP(B8,chauffeurslijst!A:B,2,0)),"",(VLOOKUP(B8,chauffeurslijst!A:B,2,0))) | D8: 42026 | E8: VL + CR | F8: zelf aangevraagd | G8: =YEAR(D8) -> 2015
A9: Ziekteverzuim | B9: 27151 | C9: =IF(ISNA(VLOOKUP(B9,chauffeurslijst!A:B,2,0)),"",(VLOOKUP(B9,chauffeurslijst!A:B,2,0))) -> De Winter Lorenzo | D9: 42026 | E9: SW | F9: gesprek over algemeen functioneren bij hervatting (deeltijds) vanaf 01/02/2015 | G9: =YEAR(D9) -> 2015
A10: Ziekteverzuim | B10: 28460 | C10: =IF(ISNA(VLOOKUP(B10,chauffeurslijst!A:B,2,0)),"",(VLOOKUP(B10,chauffeurslijst!A:B,2,0))) -> Özcam Halil | D10: 42031 | E10: CR | G10: =YEAR(D10) -> 2015
A11: Ziekteverzuim | B11: 25220 | C11: Elcin Huseyin Kursat | D11: 42086 | E11: IVC + CR | G11: =YEAR(D11) -> 2015
A12: Ziekteverzuim | B12: 14425 | C12: Vandaele Thibaut | D12: 42089 | E12: CR | G12: =YEAR(D12) -> 2015
A13: Ziekteverzuim | B13: 23164 | C13: Tillieu Patricia | D13: 42093 | E13: CR | F13: informeel | G13: =YEAR(D13) -> 2015
A14: Ziekteverzuim | B14: 29369 | C14: =IF(ISNA(VLOOKUP(B14,chauffeurslijst!A:B,2,0)),"",(VLOOKUP(B14,chauffeurslijst!A:B,2,0))) -> Vyncke Sissi | D14: 42115 | E14: SW | F14: ziekteverzuim besproken naar aanleiding van evaluatiegesprek 6 maanden | G14: =YEAR(D14) -> 2015
A15: Ziekteverzuim | B15: 26847 | C15: =IF(ISNA(VLOOKUP(B15,chauffeurslijst!A:B,2,0)),"",(VLOOKUP(B15,chauffeurslijst!A:B,2,0))) -> De Meester David | D15: 42135 | E15: SW | G15: =YEAR(D15) -> 2015
A16: Ziekteverzuim | B16: 22051 | C16: Pospiech Marcin | D16: 42137 | E16: CR | G16: =YEAR(D16) -> 2015
A17: Ziekteverzuim | B17: 27577 | C17: De Meester Johan | D17: 43238 | E17: CR | G17: =YEAR(D17) -> 2018
A18: Ziekteverzuim | B18: 19249 | C18: Odaci Kadir | D18: 42142 | E18: CR | G18: =YEAR(D18) -> 2015
A19: Ziekteverzuim | B19: 20541 | C19: Seghers Ruben | D19: 42143 | E19: CR | G19: =YEAR(D19) -> 2015
A20: Ziekteverzuim | B20: 27672 | C20: =IF(ISNA(VLOOKUP(B20,chauffeurslijst!A:B,2,0)),"",(VLOOKUP(B20,chauffeurslijst!A:B,2,0))) -> Criel Veronique | D20: 42143 | E20: SW | G20: =YEAR(D20) -> 2015
A21: Ziekteverzuim | B21: 25933 | C21: =IF(ISNA(VLOOKUP(B21,chauffeurslijst!A:B,2,0)),"",(VLOOKUP(B21,chauffeurslijst!A:B,2,0))) -> Mechthold Ralf | D21: 42144 | E21: SW | G21: =YEAR(D21) -> 2015
A22: Ziekteverzuim | B22: 14337 | C22: =IF(ISNA(VLOOKUP(B22,chauffeurslijst!A:B,2,0)),"",(VLOOKUP(B22,chauffeurslijst!A:B,2,0))) -> Cetinkaya Tuncay | D22: 42144 | E22: SW | F22: zie ook geldafgifte | G22: =YEAR(D22) -> 2015
A23: Ziekteverzuim | B23: 15184 | C23: Sven Walenta | D23: 42144 | E23: CR | G23: =YEAR(D23) -> 2015
A24: Ziekteverzuim | B24: 26524 | C24: Cynthia Bolle | D24: 42144 | E24: CR | G24: =YEAR(D24) -> 2015
A25: Ziekteverzuim | B25: 27719 | C25: =IF(ISNA(VLOOKUP(B25,chauffeurslijst!A:B,2,0)),"",(VLOOKUP(B25,chauffeurslijst!A:B,2,0))) -> Van der Cruyssen Annik | D25: 42150 | E25: SW | G25: =YEAR(D25) -> 2015
A26: Ziekteverzuim | B26: 26137 | C26: =IF(ISNA(VLOOKUP(B26,chauffeurslijst!A:B,2,0)),"",(VLOOKUP(B26,chauffeurslijst!A:B,2,0))) -> Hublau Roland | D26: 42163 | E26: CR | G26: =YEAR(D26) -> 2015
A27: Ziekteverzuim | B27: 16281 | C27: =IF(ISNA(VLOOKUP(B27,chauffeurslijst!A:B,2,0)),"",(VLOOKUP(B27,chauffeurslijst!A:B,2,0))) -> Omey Geert | D27: 42172 | E27: CR | F27: na LZ | G27: =YEAR(D27) -> 2015
A28: Ziekteverzuim | B28: 20373 | C28: =IF(ISNA(VLOOKUP(B28,chauffeurslijst!A:B,2,0)),"",(VLOOKUP(B28,chauffeurslijst!A:B,2,0))) -> Dhooge Wim | D28: 42172 | E28: CR | F28: na LZ | G28: =YEAR(D28) -> 2015
A29: Ziekteverzuim | B29: 16897 | C29: =IF(ISNA(VLOOKUP(B29,chauffeurslijst!A:B,2,0)),"",(VLOOKUP(B29,chauffeurslijst!A:B,2,0))) -> VandenDaele Andy | D29: 42181 | E29: CR | G29: =YEAR(D29) -> 2015
A30: Ziekteverzuim | B30: 20738 | C30: =IF(ISNA(VLOOKUP(B30,chauffeurslijst!A:B,2,0)),"",(VLOOKUP(B30,chauffeurslijst!A:B,2,0))) | D30: 42193 | E30: CR | F30: ontslag | G30: =YEAR(D30) -> 2015
A31: Ziekteverzuim | B31: 28828 | C31: =IF(ISNA(VLOOKUP(B31,chauffeurslijst!A:B,2,0)),"",(VLOOKUP(B31,chauffeurslijst!A:B,2,0))) -> Tek Fatih | D31: 42227 | E31: SW | F31: ziekte/ algemeen functioneren | G31: =YEAR(D31) -> 2015
A32: Ziekteverzuim | B32: 26046 | C32: =IF(ISNA(VLOOKUP(B32,chauffeurslijst!A:B,2,0)),"",(VLOOKUP(B32,chauffeurslijst!A:B,2,0))) -> Vanden Veegaete Münir | D32: 42194 | E32: CR | F32: op eigen initiatief | G32: =YEAR(D32) -> 2015
A33: Ziekteverzuim | B33: 11744 | C33: =IF(ISNA(VLOOKUP(B33,chauffeurslijst!A:B,2,0)),"",(VLOOKUP(B33,chauffeurslijst!A:B,2,0))) -> De Pauw Dorothy | D33: 42194 | E33: IVC + CR | G33: =YEAR(D33) -> 2015
A34: Ziekteverzuim | B34: 28830 | C34: =IF(ISNA(VLOOKUP(B34,chauffeurslijst!A:B,2,0)),"",(VLOOKUP(B34,chauffeurslijst!A:B,2,0))) -> Isiklar Okan | D34: 42227 | E34: SW | G34: =YEAR(D34) -> 2015
A35: Ziekteverzuim | B35: 10903 | C35: =IF(ISNA(VLOOKUP(B35,chauffeurslijst!A:B,2,0)),"",(VLOOKUP(B35,chauffeurslijst!A:B,2,0))) -> De Paepe Jeroen | D35: 42237 | E35: SW | F35: ziekte/algemeen functioneren | G35: =YEAR(D35) -> 2015
A36: Ziekteverzuim | B36: 27606 | C36: =IF(ISNA(VLOOKUP(B36,chauffeurslijst!A:B,2,0)),"",(VLOOKUP(B36,chauffeurslijst!A:B,2,0))) -> Peeters Sebastiaan | D36: 42199 | E36: IVC + CR | G36: =YEAR(D36) -> 2015
A37: Ziekteverzuim | B37: 20303 | C37: =IF(ISNA(VLOOKUP(B37,chauffeurslijst!A:B,2,0)),"",(VLOOKUP(B37,chauffeurslijst!A:B,2,0))) -> Ettaibi Moulay Abdelrani | D37: 42207 | E37: CR | F37: zelf gebeld | G37: =YEAR(D37) -> 2015
A38: Ziekteverzuim | B38: 18887 | C38: =IF(ISNA(VLOOKUP(B38,chauffeurslijst!A:B,2,0)),"",(VLOOKUP(B38,chauffeurslijst!A:B,2,0))) -> Nys Kristof | D38: 42201 | G38: =YEAR(D38) -> 2015
A39: Ziekteverzuim | B39: 19251 | C39: =IF(ISNA(VLOOKUP(B39,chauffeurslijst!A:B,2,0)),"",(VLOOKUP(B39,chauffeurslijst!A:B,2,0))) -> Vanooteghem Johnny | D39: 42242 | E39: SW | G39: =YEAR(D39) -> 2015
A40: Ziekteverzuim | B40: 29075 | C40: =IF(ISNA(VLOOKUP(B40,chauffeurslijst!A:B,2,0)),"",(VLOOKUP(B40,chauffeurslijst!A:B,2,0))) -> Ahmad Herish | D40: 42242 | E40: SW | G40: =YEAR(D40) -> 2015
A41: Ziekteverzuim | B41: 29367 | C41: =IF(ISNA(VLOOKUP(B41,chauffeurslijst!A:B,2,0)),"",(VLOOKUP(B41,chauffeurslijst!A:B,2,0))) -> De Rycke Sylvie | D41: 42243 | E41: SW | G41: =YEAR(D41) -> 2015
A42: Ziekteverzuim | B42: 28909 | C42: =IF(ISNA(VLOOKUP(B42,chauffeurslijst!A:B,2,0)),"",(VLOOKUP(B42,chauffeurslijst!A:B,2,0))) -> Uyttendaele Frank | D42: 42243 | E42: SW
A43: Ziekteverzuim | B43: 27603 | C43: =IF(ISNA(VLOOKUP(B43,chauffeurslijst!A:B,2,0)),"",(VLOOKUP(B43,chauffeurslijst!A:B,2,0))) -> El-Khadiri Youssef | D43: 42243 | E43: SW
A44: Ziekteverzuim | B44: 22770 | C44: =IF(ISNA(VLOOKUP(B44,chauffeurslijst!A:B,2,0)),"",(VLOOKUP(B44,chauffeurslijst!A:B,2,0))) -> Coussée Alex | D44: 42244 | E44: SW
A45: Ziekteverzuim | B45: 29178 | C45: =IF(ISNA(VLOOKUP(B45,chauffeurslijst!A:B,2,0)),"",(VLOOKUP(B45,chauffeurslijst!A:B,2,0))) -> Slock Jan | D45: 42244 | E45: SW
A46: Geldafgifte | B46: 2697 | C46: =IF(ISNA(VLOOKUP(B46,chauffeurslijst!A:B,2,0)),"",(VLOOKUP(B46,chauffeurslijst!A:B,2,0))) -> De Baets Marc | D46: 42017 | E46: CR | F46: tel. | G46: =YEAR(D46) -> 2015
A47: Geldafgifte | B47: 4522 | C47: =IF(ISNA(VLOOKUP(B47,chauffeurslijst!A:B,2,0)),"",(VLOOKUP(B47,chauffeurslijst!A:B,2,0))) -> Dierinck Charles | D47: 42017 | E47: CR | F47: tel. | G47: =YEAR(D47) -> 2015
A48: Geldafgifte | B48: 28125 | C48: =IF(ISNA(VLOOKUP(B48,chauffeurslijst!A:B,2,0)),"",(VLOOKUP(B48,chauffeurslijst!A:B,2,0))) -> Meersman Alex | D48: 41654 | E48: CR | G48: =YEAR(D48) -> 2014
A49: Geldafgifte | B49: 28834 | C49: =IF(ISNA(VLOOKUP(B49,chauffeurslijst!A:B,2,0)),"",(VLOOKUP(B49,chauffeurslijst!A:B,2,0))) | D49: 42020 | E49: CR | F49: tel. | G49: =YEAR(D49) -> 2015
A50: Geldafgifte | B50: 26384 | C50: =IF(ISNA(VLOOKUP(B50,chauffeurslijst!A:B,2,0)),"",(VLOOKUP(B50,chauffeurslijst!A:B,2,0))) -> Van Cauwenberg Steven | D50: 42020 | E50: CR | F50: tel. | G50: =YEAR(D50) -> 2015
A51: Geldafgifte | B51: 25487 | C51: =IF(ISNA(VLOOKUP(B51,chauffeurslijst!A:B,2,0)),"",(VLOOKUP(B51,chauffeurslijst!A:B,2,0))) -> Devos Stefaan | D51: 42020 | E51: CR | F51: tel. | G51: =YEAR(D51) -> 2015
A52: Geldafgifte | B52: 8027 | C52: =IF(ISNA(VLOOKUP(B52,chauffeurslijst!A:B,2,0)),"",(VLOOKUP(B52,chauffeurslijst!A:B,2,0))) -> De Pauw Tania | D52: 42020 | E52: CR | F52: tel. | G52: =YEAR(D52) -> 2015
A53: Geldafgifte | B53: 27865 | C53: =IF(ISNA(VLOOKUP(B53,chauffeurslijst!A:B,2,0)),"",(VLOOKUP(B53,chauffeurslijst!A:B,2,0))) -> Olenski Leonard | D53: 42023 | E53: CR | F53: tel. | G53: =YEAR(D53) -> 2015
A54: Geldafgifte | B54: 27672 | C54: =IF(ISNA(VLOOKUP(B54,chauffeurslijst!A:B,2,0)),"",(VLOOKUP(B54,chauffeurslijst!A:B,2,0))) -> Criel Veronique | D54: 42024 | E54: CR | F54: tel. | G54: =YEAR(D54) -> 2015
A55: Geldafgifte | B55: 5559 | C55: =IF(ISNA(VLOOKUP(B55,chauffeurslijst!A:B,2,0)),"",(VLOOKUP(B55,chauffeurslijst!A:B,2,0))) -> Hoste Tania | D55: 42024 | E55: CR | F55: tel. | G55: =YEAR(D55) -> 2015
A56: Geldafgifte | B56: 28738 | C56: =IF(ISNA(VLOOKUP(B56,chauffeurslijst!A:B,2,0)),"",(VLOOKUP(B56,chauffeurslijst!A:B,2,0))) -> Kerkhofs Anthony | D56: 42024 | E56: CR | F56: tel. | G56: =YEAR(D56) -> 2015
A57: Geldafgifte | B57: 28834 | C57: =IF(ISNA(VLOOKUP(B57,chauffeurslijst!A:B,2,0)),"",(VLOOKUP(B57,chauffeurslijst!A:B,2,0))) | D57: 42026 | E57: VL + CR | G57: =YEAR(D57) -> 2015
A58: Geldafgifte | B58: 17552 | C58: =IF(ISNA(VLOOKUP(B58,chauffeurslijst!A:B,2,0)),"",(VLOOKUP(B58,chauffeurslijst!A:B,2,0))) -> De Geyter Daisy | D58: 41666 | E58: SW | F58: informeel | G58: =YEAR(D58) -> 2014
A59: Geldafgifte | B59: 29317 | C59: =IF(ISNA(VLOOKUP(B59,chauffeurslijst!A:B,2,0)),"",(VLOOKUP(B59,chauffeurslijst!A:B,2,0))) | D59: 42033 | E59: CR | F59: tel. | G59: =YEAR(D59) -> 2015
A60: Geldafgifte | B60: 17552 | C60: =IF(ISNA(VLOOKUP(B60,chauffeurslijst!A:B,2,0)),"",(VLOOKUP(B60,chauffeurslijst!A:B,2,0))) -> De Geyter Daisy | D60: 42053 | E60: SW | F60: functioneel gesprek | G60: =YEAR(D60) -> 2015
A61: Geldafgifte | B61: 21124 | C61: de Ridder danny | D61: 42053 | E61: Sw | F61: tel. | G61: =YEAR(D61) -> 2015
A62: Geldafgifte | B62: 22241 | C62: =IF(ISNA(VLOOKUP(B62,chauffeurslijst!A:B,2,0)),"",(VLOOKUP(B62,chauffeurslijst!A:B,2,0))) | D62: 42055 | E62: SW | F62: op eigen initiatief (basis brief van november) | G62: =YEAR(D62) -> 2015
A63: Geldafgifte | B63: 21124 | C63: =IF(ISNA(VLOOKUP(B63,chauffeurslijst!A:B,2,0)),"",(VLOOKUP(B63,chauffeurslijst!A:B,2,0))) -> De Ridder Danny | D63: 42058 | E63: SW | F63: langs gekomenna telefonisch gesprek | G63: =YEAR(D63) -> 2015
A64: Geldafgifte | B64: 26335 | C64: Van Caelenbergh Tanguy | D64: 42060 | E64: SW | F64: gesprek voorzien, is zelf langs gekomen, saldo op 0 , rest : geen dossier | G64: =YEAR(D64) -> 2015
A65: Geldafgifte | B65: 28545 | C65: =IF(ISNA(VLOOKUP(B65,chauffeurslijst!A:B,2,0)),"",(VLOOKUP(B65,chauffeurslijst!A:B,2,0))) -> Van den Bogaert Vojtech | D65: 42060 | E65: SW | F65: beperkt negatief saldo, zal aanzuiveren, werkwijze verduidelijkt | G65: =YEAR(D65) -> 2015
A66: Geldafgifte | B66: 17555 | C66: =IF(ISNA(VLOOKUP(B66,chauffeurslijst!A:B,2,0)),"",(VLOOKUP(B66,chauffeurslijst!A:B,2,0))) -> DeBisschop Wendy | D66: 42038 | E66: SW | G66: =YEAR(D66) -> 2015
A67: Geldafgifte | B67: 21581 | C67: Vanderstraeten Franky | D67: 42079 | E67: CR | F67: tel. | G67: =YEAR(D67) -> 2015
A68: Geldafgifte | B68: 20543 | C68: Pekdemir Ilknur | D68: 42079 | E68: CR | F68: tel. | G68: =YEAR(D68) -> 2015
A69: Geldafgifte | B69: 26331 | C69: Van Semmertier Pascal | D69: 42080 | E69: CR | F69: tel. | G69: =YEAR(D69) -> 2015
A70: Geldafgifte | B70: 23700 | C70: Byosière Christof | D70: 42080 | E70: CR | F70: tel. | G70: =YEAR(D70) -> 2015
A71: Geldafgifte | B71: 26793 | C71: El Allali Rachid | D71: 42080 | E71: CR | F71: tel. | G71: =YEAR(D71) -> 2015
A72: Geldafgifte | B72: 20543 | C72: Pekdemir Ilknur | D72: 42082 | E72: CR | G72: =YEAR(D72) -> 2015
A73: Geldafgifte | B73: 14425 | C73: Vandaele Thibaut | D73: 42089 | E73: CR | G73: =YEAR(D73) -> 2015
A74: Geldafgifte | B74: 8792 | C74: =IF(ISNA(VLOOKUP(B74,chauffeurslijst!A:B,2,0)),"",(VLOOKUP(B74,chauffeurslijst!A:B,2,0))) -> VandenDaele Dave | D74: 42094 | E74: SW | F74: Tel : stort juiste bedragen (rekening klopt) maar te laat, afgesproken om vlugger te storten (en nulsaldo te bereiken) | G74: =YEAR(D74) -> 2015
A75: Geldafgifte | B75: 18624 | C75: =IF(ISNA(VLOOKUP(B75,chauffeurslijst!A:B,2,0)),"",(VLOOKUP(B75,chauffeurslijst!A:B,2,0))) -> Azahaf M'Hamed | D75: 42094 | E75: SW | F75: Tel : komt langs om stortingsgedragte bespreken | G75: =YEAR(D75) -> 2015
A76: Geldafgifte | B76: 23700 | C76: Byosière Christof | D76: 42095 | E76: CR | F76: achterstand komt in orde na 10/04 | G76: =YEAR(D76) -> 2015
A77: Geldafgifte | B77: 26335 | C77: Van Caelenbergh Tanguy | D77: 42095 | E77: CR | F77: iets foutgelopen in maart, moet nazicht doen | G77: =YEAR(D77) -> 2015
A78: Geldafgifte | B78: 5813 | C78: =IF(ISNA(VLOOKUP(B78,chauffeurslijst!A:B,2,0)),"",(VLOOKUP(B78,chauffeurslijst!A:B,2,0))) -> Binard Sabine | D78: 42095 | E78: SW | F78: rekening nagezien, saldo is - € 0,6, hoog bedrag komt door laattijdig storten, zal nu tijdig storten (wisselgeld aangevraagd). | G78: =YEAR(D78) -> 2015
A79: Geldafgifte | B79: 20303 | C79: Ettaibi Moulay Abdelrani | D79: 42103 | E79: CR | F79: tel. | G79: =YEAR(D79) -> 2015
A80: Geldafgifte | B80: 25607 | C80: Byosière Pascal | D80: 42103 | E80: CR | F80: tel. | G80: =YEAR(D80) -> 2015
A81: Geldafgifte | B81: 25875 | C81: Verstockt Debby | D81: 42103 | E81: CR | F81: tel. | G81: =YEAR(D81) -> 2015
A82: Geldafgifte | B82: 27602 | C82: Sassi Selma | D82: 42103 | E82: CR | F82: tel. | G82: =YEAR(D82) -> 2015
A83: Geldafgifte | B83: 8027 | C83: De Pauw Tania | D83: 42107 | E83: CR | G83: =YEAR(D83) -> 2015
A84: Geldafgifte | B84: 12124 | C84: Van Vliet Tom | D84: 42107 | E84: CR | F84: tel. | G84: =YEAR(D84) -> 2015
A85: Geldafgifte | B85: 15852 | C85: Petereyns Vanessa | D85: 42107 | E85: CR | F85: tel. | G85: =YEAR(D85) -> 2015
A86: Geldafgifte | B86: 18456 | C86: Van Meurs Esther | D86: 42108 | E86: CR | F86: tel. | G86: =YEAR(D86) -> 2015
A87: Geldafgifte | B87: 12121 | C87: Hautekeete Luc | D87: 42108 | E87: CR | F87: tel. | G87: =YEAR(D87) -> 2015
A88: Geldafgifte | B88: 20655 | C88: Rivière Andy | D88: 42108 | E88: CR | F88: tel. | G88: =YEAR(D88) -> 2015
A89: Geldafgifte | B89: 25935 | C89: Staelens Kris | D89: 42108 | E89: CR | F89: tel. | G89: =YEAR(D89) -> 2015
A90: Geldafgifte | B90: 26384 | C90: Van Cauwenberg Steven | D90: 42108 | E90: CR | F90: tel. | G90: =YEAR(D90) -> 2015
A91: Geldafgifte | B91: 2697 | C91: De Baets Marc | D91: 42108 | E91: CR | F91: tel. | G91: =YEAR(D91) -> 2015
A92: Geldafgifte | B92: 20478 | C92: Vanden Boer Rumold | D92: 42108 | E92: CR | F92: tel. | G92: =YEAR(D92) -> 2015
A93: Geldafgifte | B93: 15219 | C93: De Mey Peter | D93: 42109 | E93: CR | G93: =YEAR(D93) -> 2015
A94: Geldafgifte | B94: 27208 | C94: Niemegeers Marino | D94: 42111 | E94: CR | F94: voice mail | G94: =YEAR(D94) -> 2015
A95: Geldafgifte | B95: 28834 | C95: Xavier Bauweraerts | D95: 42115 | E95: IVC + CR | G95: =YEAR(D95) -> 2015
A96: Geldafgifte | B96: 28125 | C96: Meersman Alex | D96: 42121 | E96: CR | G96: =YEAR(D96) -> 2015
A97: Geldafgifte | B97: 15184 | C97: Sven Walenta | D97: 42145 | E97: CR | G97: =YEAR(D97) -> 2015
A98: Geldafgifte | B98: 26524 | C98: Cynthia Bolle | D98: 42144 | E98: CR | G98: =YEAR(D98) -> 2015
A99: Geldafgifte | B99: 26795 | C99: De Ruyck Dominique | D99: 42150 | E99: CR | G99: =YEAR(D99) -> 2015
A100: Geldafgifte | B100: 21509 | C100: =IF(ISNA(VLOOKUP(B100,chauffeurslijst!A:B,2,0)),"",(VLOOKUP(B100,chauffeurslijst!A:B,2,0))) -> De Craemer Kris | D100: 42167 | E100: SW | F100: wat slordig geweest, nu ok | G100: =YEAR(D100) -> 2015
...
